{
"meta":{"test_sets":[],"test_metrics":[],"learn_metrics":[{"best_value":"Min","name":"RMSE"}],"launch_mode":"Train","parameters":"","iteration_count":1000,"learn_sets":["learn"],"name":"experiment"},
"iterations":[
{"learn":[14.59871775],"iteration":0,"passed_time":0.1494397963,"remaining_time":149.2903565},
{"learn":[14.22518863],"iteration":1,"passed_time":0.1500217865,"remaining_time":74.86087148},
{"learn":[13.8866124],"iteration":2,"passed_time":0.1506154901,"remaining_time":50.05454788},
{"learn":[13.52356875],"iteration":3,"passed_time":0.1511970707,"remaining_time":37.6480706},
{"learn":[13.18870211],"iteration":4,"passed_time":0.1516552183,"remaining_time":30.17938844},
{"learn":[12.9124226],"iteration":5,"passed_time":0.1521036706,"remaining_time":25.19850809},
{"learn":[12.60003351],"iteration":6,"passed_time":0.1525917989,"remaining_time":21.64623661},
{"learn":[12.32990573],"iteration":7,"passed_time":0.1530587347,"remaining_time":18.97928311},
{"learn":[12.0660619],"iteration":8,"passed_time":0.1535051212,"remaining_time":16.90261946},
{"learn":[11.77309809],"iteration":9,"passed_time":0.1539590079,"remaining_time":15.24194179},
{"learn":[11.49227636],"iteration":10,"passed_time":0.1544097803,"remaining_time":13.88284298},
{"learn":[11.26264833],"iteration":11,"passed_time":0.1548674853,"remaining_time":12.75075629},
{"learn":[11.04260393],"iteration":12,"passed_time":0.1553133614,"remaining_time":11.79186829},
{"learn":[10.79916926],"iteration":13,"passed_time":0.1558002737,"remaining_time":10.9727907},
{"learn":[10.5541002],"iteration":14,"passed_time":0.1562764318,"remaining_time":10.26215235},
{"learn":[10.31918115],"iteration":15,"passed_time":0.1567473516,"remaining_time":9.639962124},
{"learn":[10.10004441],"iteration":16,"passed_time":0.1572093079,"remaining_time":9.090397037},
{"learn":[9.894556723],"iteration":17,"passed_time":0.157663369,"remaining_time":8.601412688},
{"learn":[9.690174082],"iteration":18,"passed_time":0.1581100732,"remaining_time":8.163472728},
{"learn":[9.506034866],"iteration":19,"passed_time":0.1585612892,"remaining_time":7.769503169},
{"learn":[9.338524633],"iteration":20,"passed_time":0.1590378074,"remaining_time":7.414191118},
{"learn":[9.170203312],"iteration":21,"passed_time":0.1594911968,"remaining_time":7.090108657},
{"learn":[9.010299969],"iteration":22,"passed_time":0.1599685058,"remaining_time":6.79518392},
{"learn":[8.843866678],"iteration":23,"passed_time":0.160457351,"remaining_time":6.525265609},
{"learn":[8.690548059],"iteration":24,"passed_time":0.1609062903,"remaining_time":6.275345321},
{"learn":[8.555307687],"iteration":25,"passed_time":0.1613557494,"remaining_time":6.044634614},
{"learn":[8.413851302],"iteration":26,"passed_time":0.1617993124,"remaining_time":5.830767815},
{"learn":[8.29256019],"iteration":27,"passed_time":0.162249696,"remaining_time":5.632382304},
{"learn":[8.162193833],"iteration":28,"passed_time":0.1627081109,"remaining_time":5.447916404},
{"learn":[8.040736294],"iteration":29,"passed_time":0.163150523,"remaining_time":5.275200243},
{"learn":[7.921220278],"iteration":30,"passed_time":0.163604191,"remaining_time":5.113950356},
{"learn":[7.809589039],"iteration":31,"passed_time":0.1640691643,"remaining_time":4.96309222},
{"learn":[7.699675801],"iteration":32,"passed_time":0.1645147202,"remaining_time":4.82077983},
{"learn":[7.60645267],"iteration":33,"passed_time":0.1649500938,"remaining_time":4.686523254},
{"learn":[7.498880302],"iteration":34,"passed_time":0.1654070931,"remaining_time":4.560509852},
{"learn":[7.401158744],"iteration":35,"passed_time":0.1658535603,"remaining_time":4.441189782},
{"learn":[7.306431077],"iteration":36,"passed_time":0.1662917566,"remaining_time":4.328080044},
{"learn":[7.223863468],"iteration":37,"passed_time":0.1667353839,"remaining_time":4.221037876},
{"learn":[7.143477682],"iteration":38,"passed_time":0.1671733641,"remaining_time":4.11932315},
{"learn":[7.062817131],"iteration":39,"passed_time":0.1676148422,"remaining_time":4.022756212},
{"learn":[6.990793435],"iteration":40,"passed_time":0.1680471441,"remaining_time":3.930663687},
{"learn":[6.931862224],"iteration":41,"passed_time":0.1684861268,"remaining_time":3.84308832},
{"learn":[6.858296558],"iteration":42,"passed_time":0.1689264982,"remaining_time":3.759596717},
{"learn":[6.786268161],"iteration":43,"passed_time":0.1693614336,"remaining_time":3.679762057},
{"learn":[6.717118549],"iteration":44,"passed_time":0.1697989303,"remaining_time":3.603510632},
{"learn":[6.652948106],"iteration":45,"passed_time":0.17032282,"remaining_time":3.532347181},
{"learn":[6.589686076],"iteration":46,"passed_time":0.170916692,"remaining_time":3.46560867},
{"learn":[6.531283097],"iteration":47,"passed_time":0.1715234326,"remaining_time":3.401881413},
{"learn":[6.471368031],"iteration":48,"passed_time":0.171980214,"remaining_time":3.337820071},
{"learn":[6.416481395],"iteration":49,"passed_time":0.1724351457,"remaining_time":3.276267768},
{"learn":[6.369870822],"iteration":50,"passed_time":0.1731999923,"remaining_time":3.222878287},
{"learn":[6.325678067],"iteration":51,"passed_time":0.1737435712,"remaining_time":3.167478951},
{"learn":[6.275766122],"iteration":52,"passed_time":0.1742053937,"remaining_time":3.112688828},
{"learn":[6.224773967],"iteration":53,"passed_time":0.1746637974,"remaining_time":3.059850969},
{"learn":[6.182249254],"iteration":54,"passed_time":0.1751111812,"remaining_time":3.008728477},
{"learn":[6.139904173],"iteration":55,"passed_time":0.1755580382,"remaining_time":2.959406929},
{"learn":[6.100525536],"iteration":56,"passed_time":0.1759937495,"remaining_time":2.911615891},
{"learn":[6.062568564],"iteration":57,"passed_time":0.1764348396,"remaining_time":2.865545154},
{"learn":[6.030559288],"iteration":58,"passed_time":0.1768885041,"remaining_time":2.821221735},
{"learn":[5.997931376],"iteration":59,"passed_time":0.1773356076,"remaining_time":2.778257852},
{"learn":[5.964103835],"iteration":60,"passed_time":0.1778442887,"remaining_time":2.737635854},
{"learn":[5.933729724],"iteration":61,"passed_time":0.1782837401,"remaining_time":2.697260455},
{"learn":[5.901932711],"iteration":62,"passed_time":0.1787810151,"remaining_time":2.659012876},
{"learn":[5.873727795],"iteration":63,"passed_time":0.179225854,"remaining_time":2.621178115},
{"learn":[5.846485734],"iteration":64,"passed_time":0.1796762124,"remaining_time":2.584573209},
{"learn":[5.820630862],"iteration":65,"passed_time":0.1801133359,"remaining_time":2.548876602},
{"learn":[5.793646238],"iteration":66,"passed_time":0.1805527361,"remaining_time":2.514264221},
{"learn":[5.765388646],"iteration":67,"passed_time":0.1811423754,"remaining_time":2.482716086},
{"learn":[5.747073912],"iteration":68,"passed_time":0.181597157,"remaining_time":2.450245698},
{"learn":[5.722315217],"iteration":69,"passed_time":0.1820367386,"remaining_time":2.418488098},
{"learn":[5.699970599],"iteration":70,"passed_time":0.1824755199,"remaining_time":2.387602225},
{"learn":[5.682732647],"iteration":71,"passed_time":0.1829195994,"remaining_time":2.357630392},
{"learn":[5.663525791],"iteration":72,"passed_time":0.1833568669,"remaining_time":2.328381036},
{"learn":[5.642381613],"iteration":73,"passed_time":0.1837998198,"remaining_time":2.299981528},
{"learn":[5.621404779],"iteration":74,"passed_time":0.1842303657,"remaining_time":2.272174511},
{"learn":[5.602460129],"iteration":75,"passed_time":0.1847059162,"remaining_time":2.245635087},
{"learn":[5.587337574],"iteration":76,"passed_time":0.1852278539,"remaining_time":2.22032869},
{"learn":[5.572393026],"iteration":77,"passed_time":0.1857040206,"remaining_time":2.195116757},
{"learn":[5.558425806],"iteration":78,"passed_time":0.1862570396,"remaining_time":2.171427006},
{"learn":[5.541518902],"iteration":79,"passed_time":0.1868562184,"remaining_time":2.148846512},
{"learn":[5.526157283],"iteration":80,"passed_time":0.1873230475,"remaining_time":2.125307168},
{"learn":[5.511746977],"iteration":81,"passed_time":0.1877782266,"remaining_time":2.102200146},
{"learn":[5.504975022],"iteration":82,"passed_time":0.1880367334,"remaining_time":2.077466079},
{"learn":[5.493980522],"iteration":83,"passed_time":0.1885183597,"remaining_time":2.055747827},
{"learn":[5.480745463],"iteration":84,"passed_time":0.1889992144,"remaining_time":2.034520955},
{"learn":[5.464052013],"iteration":85,"passed_time":0.1894566598,"remaining_time":2.013527756},
{"learn":[5.449143727],"iteration":86,"passed_time":0.189898427,"remaining_time":1.992842113},
{"learn":[5.438255432],"iteration":87,"passed_time":0.1903412799,"remaining_time":1.97262781},
{"learn":[5.425927931],"iteration":88,"passed_time":0.1907915698,"remaining_time":1.952933933},
{"learn":[5.412331217],"iteration":89,"passed_time":0.1912445008,"remaining_time":1.933694397},
{"learn":[5.400691499],"iteration":90,"passed_time":0.1917150344,"remaining_time":1.915043585},
{"learn":[5.391618744],"iteration":91,"passed_time":0.1921739883,"remaining_time":1.896673711},
{"learn":[5.380766572],"iteration":92,"passed_time":0.1926342286,"remaining_time":1.878701563},
{"learn":[5.372207183],"iteration":93,"passed_time":0.1930787151,"remaining_time":1.860950169},
{"learn":[5.362918837],"iteration":94,"passed_time":0.1935172378,"remaining_time":1.843506318},
{"learn":[5.348292324],"iteration":95,"passed_time":0.1939565347,"remaining_time":1.826424035},
{"learn":[5.339772295],"iteration":96,"passed_time":0.1943869965,"remaining_time":1.809602658},
{"learn":[5.331515983],"iteration":97,"passed_time":0.1948197888,"remaining_time":1.79313724},
{"learn":[5.323861644],"iteration":98,"passed_time":0.1952566623,"remaining_time":1.777032856},
{"learn":[5.313277281],"iteration":99,"passed_time":0.1956992315,"remaining_time":1.761293083},
{"learn":[5.30685627],"iteration":100,"passed_time":0.1961311766,"remaining_time":1.745761661},
{"learn":[5.29652059],"iteration":101,"passed_time":0.1965723961,"remaining_time":1.730607958},
{"learn":[5.288350766],"iteration":102,"passed_time":0.1970077715,"remaining_time":1.715689039},
{"learn":[5.27993346],"iteration":103,"passed_time":0.1974519334,"remaining_time":1.701124349},
{"learn":[5.271789139],"iteration":104,"passed_time":0.1978933898,"remaining_time":1.686805561},
{"learn":[5.262684686],"iteration":105,"passed_time":0.1983232076,"remaining_time":1.672650449},
{"learn":[5.251619772],"iteration":106,"passed_time":0.1987781862,"remaining_time":1.658961872},
{"learn":[5.241012171],"iteration":107,"passed_time":0.1992234253,"remaining_time":1.64543792},
{"learn":[5.232684032],"iteration":108,"passed_time":0.1998745849,"remaining_time":1.633837203},
{"learn":[5.224267141],"iteration":109,"passed_time":0.2004594455,"remaining_time":1.62189915},
{"learn":[5.216324968],"iteration":110,"passed_time":0.2010786741,"remaining_time":1.610440912},
{"learn":[5.211102527],"iteration":111,"passed_time":0.2016777123,"remaining_time":1.599016147},
{"learn":[5.206364257],"iteration":112,"passed_time":0.2022798196,"remaining_time":1.587807079},
{"learn":[5.196937641],"iteration":113,"passed_time":0.2028747374,"remaining_time":1.576728223},
{"learn":[5.190746047],"iteration":114,"passed_time":0.2033774521,"remaining_time":1.565122131},
{"learn":[5.181885213],"iteration":115,"passed_time":0.2039040326,"remaining_time":1.553889352},
{"learn":[5.178293568],"iteration":116,"passed_time":0.2043213055,"remaining_time":1.542014639},
{"learn":[5.170991438],"iteration":117,"passed_time":0.2047795555,"remaining_time":1.530640406},
{"learn":[5.166257212],"iteration":118,"passed_time":0.2052201274,"remaining_time":1.519318759},
{"learn":[5.161421246],"iteration":119,"passed_time":0.2056500641,"remaining_time":1.50810047},
{"learn":[5.158223542],"iteration":120,"passed_time":0.2060926263,"remaining_time":1.497152219},
{"learn":[5.15470988],"iteration":121,"passed_time":0.206443336,"remaining_time":1.485715155},
{"learn":[5.146388143],"iteration":122,"passed_time":0.20688064,"remaining_time":1.475075783},
{"learn":[5.139529364],"iteration":123,"passed_time":0.2073792396,"remaining_time":1.465033983},
{"learn":[5.134276023],"iteration":124,"passed_time":0.2078110068,"remaining_time":1.454677047},
{"learn":[5.128536065],"iteration":125,"passed_time":0.2082543771,"remaining_time":1.444558139},
{"learn":[5.123300353],"iteration":126,"passed_time":0.2085990986,"remaining_time":1.433913489},
{"learn":[5.116200518],"iteration":127,"passed_time":0.2090281855,"remaining_time":1.424004514},
{"learn":[5.108728704],"iteration":128,"passed_time":0.2095138852,"remaining_time":1.41462476},
{"learn":[5.104075866],"iteration":129,"passed_time":0.2100117609,"remaining_time":1.405463323},
{"learn":[5.100317606],"iteration":130,"passed_time":0.2104474522,"remaining_time":1.396021649},
{"learn":[5.095814182],"iteration":131,"passed_time":0.2108844802,"remaining_time":1.386725218},
{"learn":[5.092146915],"iteration":132,"passed_time":0.2113208954,"remaining_time":1.377558018},
{"learn":[5.085258329],"iteration":133,"passed_time":0.211779701,"remaining_time":1.368665829},
{"learn":[5.079219421],"iteration":134,"passed_time":0.2122280968,"remaining_time":1.35983188},
{"learn":[5.076476829],"iteration":135,"passed_time":0.2126603996,"remaining_time":1.351019009},
{"learn":[5.072133867],"iteration":136,"passed_time":0.2131103483,"remaining_time":1.342439639},
{"learn":[5.067031564],"iteration":137,"passed_time":0.2135546256,"remaining_time":1.333942662},
{"learn":[5.061358312],"iteration":138,"passed_time":0.2139987823,"remaining_time":1.325560803},
{"learn":[5.056759124],"iteration":139,"passed_time":0.2146804838,"remaining_time":1.318751544},
{"learn":[5.050254],"iteration":140,"passed_time":0.2153308189,"remaining_time":1.311838109},
{"learn":[5.048376474],"iteration":141,"passed_time":0.2156962659,"remaining_time":1.303291522},
{"learn":[5.042603751],"iteration":142,"passed_time":0.2162416059,"remaining_time":1.295937456},
{"learn":[5.037477349],"iteration":143,"passed_time":0.2168202275,"remaining_time":1.288875797},
{"learn":[5.03230489],"iteration":144,"passed_time":0.2173295214,"remaining_time":1.281494764},
{"learn":[5.025976187],"iteration":145,"passed_time":0.2178072766,"remaining_time":1.274023385},
{"learn":[5.01952451],"iteration":146,"passed_time":0.218332115,"remaining_time":1.266920368},
{"learn":[5.017569424],"iteration":147,"passed_time":0.2187967837,"remaining_time":1.259559863},
{"learn":[5.008962367],"iteration":148,"passed_time":0.2192427909,"remaining_time":1.252185336},
{"learn":[5.003880266],"iteration":149,"passed_time":0.2196915696,"remaining_time":1.244918894},
{"learn":[4.996387564],"iteration":150,"passed_time":0.2201362575,"remaining_time":1.237719752},
{"learn":[4.993361683],"iteration":151,"passed_time":0.2205837307,"remaining_time":1.230625024},
{"learn":[4.99005752],"iteration":152,"passed_time":0.221019685,"remaining_time":1.22355342},
{"learn":[4.986908764],"iteration":153,"passed_time":0.2214556376,"remaining_time":1.216567983},
{"learn":[4.985207175],"iteration":154,"passed_time":0.2218961879,"remaining_time":1.209692121},
{"learn":[4.979003494],"iteration":155,"passed_time":0.2223404678,"remaining_time":1.202918941},
{"learn":[4.973142217],"iteration":156,"passed_time":0.2228502539,"remaining_time":1.196578115},
{"learn":[4.967056696],"iteration":157,"passed_time":0.2232883373,"remaining_time":1.189928988},
{"learn":[4.961460696],"iteration":158,"passed_time":0.2237333481,"remaining_time":1.183394627},
{"learn":[4.954240363],"iteration":159,"passed_time":0.2241705037,"remaining_time":1.176895145},
{"learn":[4.952320707],"iteration":160,"passed_time":0.2244592426,"remaining_time":1.169697544},
{"learn":[4.948337777],"iteration":161,"passed_time":0.2248965145,"remaining_time":1.163353575},
{"learn":[4.943228639],"iteration":162,"passed_time":0.2253316651,"remaining_time":1.157071188},
{"learn":[4.938545759],"iteration":163,"passed_time":0.2257700697,"remaining_time":1.150876697},
{"learn":[4.935330572],"iteration":164,"passed_time":0.2262044035,"remaining_time":1.144731375},
{"learn":[4.932051543],"iteration":165,"passed_time":0.2266429123,"remaining_time":1.138675837},
{"learn":[4.928964153],"iteration":166,"passed_time":0.2270733168,"remaining_time":1.132647143},
{"learn":[4.922860227],"iteration":167,"passed_time":0.2275087,"remaining_time":1.126709752},
{"learn":[4.917668772],"iteration":168,"passed_time":0.2279677373,"remaining_time":1.120953785},
{"learn":[4.910365386],"iteration":169,"passed_time":0.2284101016,"remaining_time":1.115178731},
{"learn":[4.906457206],"iteration":170,"passed_time":0.2288636854,"remaining_time":1.10952044},
{"learn":[4.901996508],"iteration":171,"passed_time":0.2294853994,"remaining_time":1.104732039},
{"learn":[4.896816173],"iteration":172,"passed_time":0.2300216808,"remaining_time":1.09958341},
{"learn":[4.891123132],"iteration":173,"passed_time":0.2305364477,"remaining_time":1.094385665},
{"learn":[4.887630202],"iteration":174,"passed_time":0.2310390278,"remaining_time":1.089183988},
{"learn":[4.885259712],"iteration":175,"passed_time":0.2315218072,"remaining_time":1.083943006},
{"learn":[4.880659728],"iteration":176,"passed_time":0.2320790888,"remaining_time":1.079102204},
{"learn":[4.877299723],"iteration":177,"passed_time":0.2325904945,"remaining_time":1.074097677},
{"learn":[4.874038772],"iteration":178,"passed_time":0.2330367577,"remaining_time":1.06884457},
{"learn":[4.86943698],"iteration":179,"passed_time":0.2334684555,"remaining_time":1.06357852},
{"learn":[4.861268711],"iteration":180,"passed_time":0.2339077411,"remaining_time":1.058400221},
{"learn":[4.858673056],"iteration":181,"passed_time":0.2343451155,"remaining_time":1.053265409},
{"learn":[4.854036207],"iteration":182,"passed_time":0.2347808476,"remaining_time":1.048174604},
{"learn":[4.85130244],"iteration":183,"passed_time":0.2352171187,"remaining_time":1.043136787},
{"learn":[4.847510084],"iteration":184,"passed_time":0.2356465728,"remaining_time":1.038118686},
{"learn":[4.845691673],"iteration":185,"passed_time":0.2360759757,"remaining_time":1.0331497},
{"learn":[4.842058646],"iteration":186,"passed_time":0.236514849,"remaining_time":1.02827044},
{"learn":[4.838623675],"iteration":187,"passed_time":0.2369469487,"remaining_time":1.023409161},
{"learn":[4.834602161],"iteration":188,"passed_time":0.2373862681,"remaining_time":1.018625733},
{"learn":[4.830858976],"iteration":189,"passed_time":0.2378209136,"remaining_time":1.013868105},
{"learn":[4.827590511],"iteration":190,"passed_time":0.2382517356,"remaining_time":1.00913955},
{"learn":[4.822246226],"iteration":191,"passed_time":0.2386965111,"remaining_time":1.004514484},
{"learn":[4.816686395],"iteration":192,"passed_time":0.2391289788,"remaining_time":0.9998812741},
{"learn":[4.814797121],"iteration":193,"passed_time":0.2395819984,"remaining_time":0.9953767562},
{"learn":[4.811639392],"iteration":194,"passed_time":0.2400170257,"remaining_time":0.9908395165},
{"learn":[4.804813432],"iteration":195,"passed_time":0.2404512007,"remaining_time":0.9863406397},
{"learn":[4.80251613],"iteration":196,"passed_time":0.2409158342,"remaining_time":0.9820071822},
{"learn":[4.800087884],"iteration":197,"passed_time":0.2414392796,"remaining_time":0.9779510214},
{"learn":[4.794773135],"iteration":198,"passed_time":0.2419793406,"remaining_time":0.9739972452},
{"learn":[4.791664833],"iteration":199,"passed_time":0.2424160014,"remaining_time":0.9696640058},
{"learn":[4.785989873],"iteration":200,"passed_time":0.2428669448,"remaining_time":0.9654263131},
{"learn":[4.782387142],"iteration":201,"passed_time":0.2433173839,"remaining_time":0.9612241207},
{"learn":[4.778623704],"iteration":202,"passed_time":0.2437673517,"remaining_time":0.957057041},
{"learn":[4.775772178],"iteration":203,"passed_time":0.2443393073,"remaining_time":0.9534023953},
{"learn":[4.77023101],"iteration":204,"passed_time":0.2448893431,"remaining_time":0.9496928183},
{"learn":[4.764496689],"iteration":205,"passed_time":0.2453703731,"remaining_time":0.9457479429},
{"learn":[4.763138716],"iteration":206,"passed_time":0.2458090338,"remaining_time":0.9416742212},
{"learn":[4.758053283],"iteration":207,"passed_time":0.2462652145,"remaining_time":0.937702163},
{"learn":[4.755063788],"iteration":208,"passed_time":0.2467837497,"remaining_time":0.9339997418},
{"learn":[4.752465267],"iteration":209,"passed_time":0.2472660991,"remaining_time":0.9301915156},
{"learn":[4.748067377],"iteration":210,"passed_time":0.2477329846,"remaining_time":0.9263569897},
{"learn":[4.744163298],"iteration":211,"passed_time":0.2482069788,"remaining_time":0.9225806569},
{"learn":[4.736670896],"iteration":212,"passed_time":0.2487311376,"remaining_time":0.9190206821},
{"learn":[4.73349255],"iteration":213,"passed_time":0.2492380524,"remaining_time":0.9154257437},
{"learn":[4.731864595],"iteration":214,"passed_time":0.2496849197,"remaining_time":0.9116402883},
{"learn":[4.728398311],"iteration":215,"passed_time":0.2501344518,"remaining_time":0.9078954177},
{"learn":[4.723865975],"iteration":216,"passed_time":0.2505691415,"remaining_time":0.9041273631},
{"learn":[4.723483365],"iteration":217,"passed_time":0.2509993707,"remaining_time":0.9003738893},
{"learn":[4.72095416],"iteration":218,"passed_time":0.2514344596,"remaining_time":0.8966680958},
{"learn":[4.716173382],"iteration":219,"passed_time":0.2518999468,"remaining_time":0.8930998114},
{"learn":[4.710563974],"iteration":220,"passed_time":0.2523608606,"remaining_time":0.8895434861},
{"learn":[4.707160263],"iteration":221,"passed_time":0.2528128551,"remaining_time":0.8859837897},
{"learn":[4.70408351],"iteration":222,"passed_time":0.2532559902,"remaining_time":0.882421096},
{"learn":[4.702501831],"iteration":223,"passed_time":0.253697964,"remaining_time":0.8788822323},
{"learn":[4.700269738],"iteration":224,"passed_time":0.2541217667,"remaining_time":0.8753083074},
{"learn":[4.695346302],"iteration":225,"passed_time":0.2545498033,"remaining_time":0.8717767601},
{"learn":[4.689769299],"iteration":226,"passed_time":0.2550903209,"remaining_time":0.868655586},
{"learn":[4.687919514],"iteration":227,"passed_time":0.2555519542,"remaining_time":0.8652899503},
{"learn":[4.682982074],"iteration":228,"passed_time":0.2560615233,"remaining_time":0.8621110674},
{"learn":[4.679578702],"iteration":229,"passed_time":0.2565877947,"remaining_time":0.8590113128},
{"learn":[4.675751423],"iteration":230,"passed_time":0.2570417795,"remaining_time":0.8556931968},
{"learn":[4.672710726],"iteration":231,"passed_time":0.2576196174,"remaining_time":0.8528097679},
{"learn":[4.6690533],"iteration":232,"passed_time":0.2580941037,"remaining_time":0.8496059123},
{"learn":[4.667595702],"iteration":233,"passed_time":0.258635162,"remaining_time":0.8466433082},
{"learn":[4.664241291],"iteration":234,"passed_time":0.2592062462,"remaining_time":0.8437990567},
{"learn":[4.662246999],"iteration":235,"passed_time":0.2598009401,"remaining_time":0.8410505011},
{"learn":[4.658668443],"iteration":236,"passed_time":0.2603644781,"remaining_time":0.8382198177},
{"learn":[4.658017572],"iteration":237,"passed_time":0.2608053738,"remaining_time":0.8350155246},
{"learn":[4.657656705],"iteration":238,"passed_time":0.2612175838,"remaining_time":0.831743018},
{"learn":[4.653242871],"iteration":239,"passed_time":0.2616447898,"remaining_time":0.8285418345},
{"learn":[4.6507302],"iteration":240,"passed_time":0.2620734107,"remaining_time":0.8253681273},
{"learn":[4.647671336],"iteration":241,"passed_time":0.262570105,"remaining_time":0.8224303289},
{"learn":[4.645506007],"iteration":242,"passed_time":0.2630653195,"remaining_time":0.8195080117},
{"learn":[4.641297906],"iteration":243,"passed_time":0.2635565595,"remaining_time":0.8165932744},
{"learn":[4.63798107],"iteration":244,"passed_time":0.2639910634,"remaining_time":0.8135234811},
{"learn":[4.635062318],"iteration":245,"passed_time":0.2644223446,"remaining_time":0.810465235},
{"learn":[4.631606017],"iteration":246,"passed_time":0.2648643452,"remaining_time":0.8074609391},
{"learn":[4.630215494],"iteration":247,"passed_time":0.265301546,"remaining_time":0.8044627523},
{"learn":[4.62729814],"iteration":248,"passed_time":0.2657698072,"remaining_time":0.8015788161},
{"learn":[4.624691756],"iteration":249,"passed_time":0.2662011474,"remaining_time":0.7986034421},
{"learn":[4.621840053],"iteration":250,"passed_time":0.2666350741,"remaining_time":0.7956560578},
{"learn":[4.619602091],"iteration":251,"passed_time":0.2670632314,"remaining_time":0.7927114965},
{"learn":[4.613584029],"iteration":252,"passed_time":0.2674882736,"remaining_time":0.7897776299},
{"learn":[4.6119388],"iteration":253,"passed_time":0.2679191407,"remaining_time":0.7868806259},
{"learn":[4.60870702],"iteration":254,"passed_time":0.2683486017,"remaining_time":0.783998856},
{"learn":[4.604771557],"iteration":255,"passed_time":0.2687827672,"remaining_time":0.7811499171},
{"learn":[4.604231277],"iteration":256,"passed_time":0.2692464238,"remaining_time":0.7784050306},
{"learn":[4.600750354],"iteration":257,"passed_time":0.2696839379,"remaining_time":0.775602643},
{"learn":[4.596488253],"iteration":258,"passed_time":0.2701199721,"remaining_time":0.772814283},
{"learn":[4.59470784],"iteration":259,"passed_time":0.2705614398,"remaining_time":0.7700594824},
{"learn":[4.588818005],"iteration":260,"passed_time":0.271002181,"remaining_time":0.7673203515},
{"learn":[4.585054174],"iteration":261,"passed_time":0.271439406,"remaining_time":0.7645888613},
{"learn":[4.581471435],"iteration":262,"passed_time":0.2718751503,"remaining_time":0.7618706684},
{"learn":[4.577555199],"iteration":263,"passed_time":0.272310248,"remaining_time":0.759167964},
{"learn":[4.57457145],"iteration":264,"passed_time":0.2727486804,"remaining_time":0.7564916229},
{"learn":[4.573029224],"iteration":265,"passed_time":0.2731737798,"remaining_time":0.7537953172},
{"learn":[4.571326203],"iteration":266,"passed_time":0.273610419,"remaining_time":0.7511477045},
{"learn":[4.571019224],"iteration":267,"passed_time":0.2740933481,"remaining_time":0.7486430254},
{"learn":[4.565766631],"iteration":268,"passed_time":0.274640306,"remaining_time":0.7463273744},
{"learn":[4.563383471],"iteration":269,"passed_time":0.2751623149,"remaining_time":0.7439573698},
{"learn":[4.558165805],"iteration":270,"passed_time":0.2756726286,"remaining_time":0.7415695434},
{"learn":[4.55629209],"iteration":271,"passed_time":0.2761164954,"remaining_time":0.7390176789},
{"learn":[4.549383848],"iteration":272,"passed_time":0.2766126195,"remaining_time":0.736620419},
{"learn":[4.546227503],"iteration":273,"passed_time":0.2771054618,"remaining_time":0.7342283404},
{"learn":[4.540620977],"iteration":274,"passed_time":0.2776306978,"remaining_time":0.731935476},
{"learn":[4.532898237],"iteration":275,"passed_time":0.2781647203,"remaining_time":0.7296784691},
{"learn":[4.529757367],"iteration":276,"passed_time":0.2786533273,"remaining_time":0.7273153632},
{"learn":[4.52579294],"iteration":277,"passed_time":0.2791090263,"remaining_time":0.7248802769},
{"learn":[4.521572155],"iteration":278,"passed_time":0.2795538939,"remaining_time":0.7224313888},
{"learn":[4.518818099],"iteration":279,"passed_time":0.2800053928,"remaining_time":0.7200138671},
{"learn":[4.514012334],"iteration":280,"passed_time":0.2804898955,"remaining_time":0.7176947861},
{"learn":[4.508331416],"iteration":281,"passed_time":0.2809351693,"remaining_time":0.7152888354},
{"learn":[4.506038537],"iteration":282,"passed_time":0.2813736052,"remaining_time":0.7128794167},
{"learn":[4.505805643],"iteration":283,"passed_time":0.2818107157,"remaining_time":0.7104805367},
{"learn":[4.501550352],"iteration":284,"passed_time":0.282240004,"remaining_time":0.7080757994},
{"learn":[4.494692643],"iteration":285,"passed_time":0.2826821964,"remaining_time":0.7057170918},
{"learn":[4.489330245],"iteration":286,"passed_time":0.2831470773,"remaining_time":0.703428105},
{"learn":[4.484826955],"iteration":287,"passed_time":0.2835913781,"remaining_time":0.701100907},
{"learn":[4.478285428],"iteration":288,"passed_time":0.2840377837,"remaining_time":0.6987919177},
{"learn":[4.475311671],"iteration":289,"passed_time":0.284481503,"remaining_time":0.6964891969},
{"learn":[4.471581298],"iteration":290,"passed_time":0.284916999,"remaining_time":0.6941792175},
{"learn":[4.469164956],"iteration":291,"passed_time":0.2853491316,"remaining_time":0.6918739219},
{"learn":[4.462068024],"iteration":292,"passed_time":0.2858027831,"remaining_time":0.6896333367},
{"learn":[4.458540976],"iteration":293,"passed_time":0.286246781,"remaining_time":0.6873817257},
{"learn":[4.455757458],"iteration":294,"passed_time":0.2866878815,"remaining_time":0.6851354457},
{"learn":[4.453027414],"iteration":295,"passed_time":0.2871282113,"remaining_time":0.6828995297},
{"learn":[4.450659338],"iteration":296,"passed_time":0.2875668191,"remaining_time":0.680671629},
{"learn":[4.444696901],"iteration":297,"passed_time":0.2880075073,"remaining_time":0.6784606381},
{"learn":[4.442052813],"iteration":298,"passed_time":0.2884735934,"remaining_time":0.6763210334},
{"learn":[4.440036756],"iteration":299,"passed_time":0.2889501334,"remaining_time":0.6742169779},
{"learn":[4.435017051],"iteration":300,"passed_time":0.2894504411,"remaining_time":0.6721789314},
{"learn":[4.429962125],"iteration":301,"passed_time":0.2899855542,"remaining_time":0.6702315128},
{"learn":[4.427666256],"iteration":302,"passed_time":0.2904418417,"remaining_time":0.6681120914},
{"learn":[4.425030004],"iteration":303,"passed_time":0.2909529931,"remaining_time":0.666129221},
{"learn":[4.422588771],"iteration":304,"passed_time":0.2913921051,"remaining_time":0.6639918461},
{"learn":[4.418936667],"iteration":305,"passed_time":0.2918705178,"remaining_time":0.6619547037},
{"learn":[4.416887976],"iteration":306,"passed_time":0.2923209022,"remaining_time":0.6598644469},
{"learn":[4.413773354],"iteration":307,"passed_time":0.2927608249,"remaining_time":0.6577613338},
{"learn":[4.411129391],"iteration":308,"passed_time":0.293195236,"remaining_time":0.6556566603},
{"learn":[4.40850819],"iteration":309,"passed_time":0.2936371359,"remaining_time":0.6535794316},
{"learn":[4.404880292],"iteration":310,"passed_time":0.2940708457,"remaining_time":0.6514945745},
{"learn":[4.404593827],"iteration":311,"passed_time":0.2944985508,"remaining_time":0.6494070607},
{"learn":[4.402139942],"iteration":312,"passed_time":0.2949321321,"remaining_time":0.6473430502},
{"learn":[4.400284725],"iteration":313,"passed_time":0.2953741258,"remaining_time":0.6453078034},
{"learn":[4.395805521],"iteration":314,"passed_time":0.2958151985,"remaining_time":0.6432806698},
{"learn":[4.392838833],"iteration":315,"passed_time":0.2962484882,"remaining_time":0.6412467276},
{"learn":[4.389213061],"iteration":316,"passed_time":0.2967260164,"remaining_time":0.6393181993},
{"learn":[4.3861981],"iteration":317,"passed_time":0.2971726008,"remaining_time":0.6373324331},
{"learn":[4.385054234],"iteration":318,"passed_time":0.297618503,"remaining_time":0.6353548606},
{"learn":[4.379364607],"iteration":319,"passed_time":0.2980526354,"remaining_time":0.6333618503},
{"learn":[4.378387619],"iteration":320,"passed_time":0.2984767341,"remaining_time":0.6313573285},
{"learn":[4.375816727],"iteration":321,"passed_time":0.2989165214,"remaining_time":0.6293956569},
{"learn":[4.374600202],"iteration":322,"passed_time":0.2993456378,"remaining_time":0.6274210428},
{"learn":[4.37098897],"iteration":323,"passed_time":0.2997887929,"remaining_time":0.6254852592},
{"learn":[4.367418484],"iteration":324,"passed_time":0.3002287798,"remaining_time":0.6235520812},
{"learn":[4.363584638],"iteration":325,"passed_time":0.3006680238,"remaining_time":0.6216265277},
{"learn":[4.360770706],"iteration":326,"passed_time":0.3011180845,"remaining_time":0.6197323267},
{"learn":[4.358675808],"iteration":327,"passed_time":0.3015612152,"remaining_time":0.6178327336},
{"learn":[4.354228195],"iteration":328,"passed_time":0.3019994254,"remaining_time":0.6159319588},
{"learn":[4.353773425],"iteration":329,"passed_time":0.3024334355,"remaining_time":0.6140315205},
{"learn":[4.351648009],"iteration":330,"passed_time":0.3028633582,"remaining_time":0.6121316818},
{"learn":[4.348209927],"iteration":331,"passed_time":0.3032908429,"remaining_time":0.6102357923},
{"learn":[4.345852733],"iteration":332,"passed_time":0.3037529584,"remaining_time":0.6084180879},
{"learn":[4.34237339],"iteration":333,"passed_time":0.304431691,"remaining_time":0.6070404377},
{"learn":[4.340814362],"iteration":334,"passed_time":0.3049248267,"remaining_time":0.6052985365},
{"learn":[4.339707068],"iteration":335,"passed_time":0.3053579028,"remaining_time":0.6034453793},
{"learn":[4.335430786],"iteration":336,"passed_time":0.3058827694,"remaining_time":0.6017812348},
{"learn":[4.33521887],"iteration":337,"passed_time":0.3063192072,"remaining_time":0.5999506367},
{"learn":[4.328507238],"iteration":338,"passed_time":0.306758222,"remaining_time":0.5981332884},
{"learn":[4.326140732],"iteration":339,"passed_time":0.307198367,"remaining_time":0.5963262417},
{"learn":[4.323785636],"iteration":340,"passed_time":0.3076285631,"remaining_time":0.5945079857},
{"learn":[4.320632534],"iteration":341,"passed_time":0.3080610638,"remaining_time":0.5927022807},
{"learn":[4.31973724],"iteration":342,"passed_time":0.3085137649,"remaining_time":0.5909432755},
{"learn":[4.318000924],"iteration":343,"passed_time":0.3090135162,"remaining_time":0.5892815891},
{"learn":[4.312713628],"iteration":344,"passed_time":0.3094527897,"remaining_time":0.5875118181},
{"learn":[4.308220789],"iteration":345,"passed_time":0.3098926898,"remaining_time":0.5857509224},
{"learn":[4.305890947],"iteration":346,"passed_time":0.3103272797,"remaining_time":0.5839876474},
{"learn":[4.305137856],"iteration":347,"passed_time":0.3107817549,"remaining_time":0.5822692649},
{"learn":[4.304787172],"iteration":348,"passed_time":0.3113032603,"remaining_time":0.5806831589},
{"learn":[4.30350134],"iteration":349,"passed_time":0.3118062466,"remaining_time":0.5790687437},
{"learn":[4.30293809],"iteration":350,"passed_time":0.3123374308,"remaining_time":0.5775127995},
{"learn":[4.299548459],"iteration":351,"passed_time":0.3127761028,"remaining_time":0.5757923711},
{"learn":[4.294768408],"iteration":352,"passed_time":0.3133183138,"remaining_time":0.5742689773},
{"learn":[4.294581479],"iteration":353,"passed_time":0.313771086,"remaining_time":0.572587914},
{"learn":[4.292551604],"iteration":354,"passed_time":0.3142356818,"remaining_time":0.5709352528},
{"learn":[4.288628894],"iteration":355,"passed_time":0.3147559486,"remaining_time":0.5693899744},
{"learn":[4.287802767],"iteration":356,"passed_time":0.3153190916,"remaining_time":0.5679276636},
{"learn":[4.284566905],"iteration":357,"passed_time":0.315804412,"remaining_time":0.5663308171},
{"learn":[4.27890232],"iteration":358,"passed_time":0.3163297982,"remaining_time":0.5648117009},
{"learn":[4.276938023],"iteration":359,"passed_time":0.3168319321,"remaining_time":0.5632567682},
{"learn":[4.273425094],"iteration":360,"passed_time":0.3173203208,"remaining_time":0.561683338},
{"learn":[4.269726505],"iteration":361,"passed_time":0.3178370559,"remaining_time":0.5601658609},
{"learn":[4.265565857],"iteration":362,"passed_time":0.3183220421,"remaining_time":0.5585981841},
{"learn":[4.262117173],"iteration":363,"passed_time":0.3190084389,"remaining_time":0.5573883713},
{"learn":[4.259185148],"iteration":364,"passed_time":0.3195841585,"remaining_time":0.5559888784},
{"learn":[4.257668507],"iteration":365,"passed_time":0.320099901,"remaining_time":0.5544899924},
{"learn":[4.253432436],"iteration":366,"passed_time":0.3206294274,"remaining_time":0.5530202385},
{"learn":[4.250216667],"iteration":367,"passed_time":0.3211268495,"remaining_time":0.5515004589},
{"learn":[4.24514828],"iteration":368,"passed_time":0.3215778806,"remaining_time":0.5499068906},
{"learn":[4.244015772],"iteration":369,"passed_time":0.3220491333,"remaining_time":0.5483539296},
{"learn":[4.240329192],"iteration":370,"passed_time":0.3225183141,"remaining_time":0.5468032873},
{"learn":[4.236718014],"iteration":371,"passed_time":0.3229659557,"remaining_time":0.5452220973},
{"learn":[4.233495944],"iteration":372,"passed_time":0.3234019517,"remaining_time":0.5436274095},
{"learn":[4.230357491],"iteration":373,"passed_time":0.3238444176,"remaining_time":0.5420497471},
{"learn":[4.227381215],"iteration":374,"passed_time":0.3242838933,"remaining_time":0.5404731556},
{"learn":[4.226169067],"iteration":375,"passed_time":0.3247612778,"remaining_time":0.5389655249},
{"learn":[4.225963861],"iteration":376,"passed_time":0.3252963853,"remaining_time":0.5375587481},
{"learn":[4.224346548],"iteration":377,"passed_time":0.3257773914,"remaining_time":0.5360675595},
{"learn":[4.222595381],"iteration":378,"passed_time":0.3262119891,"remaining_time":0.5345056603},
{"learn":[4.219700938],"iteration":379,"passed_time":0.3266542667,"remaining_time":0.5329622246},
{"learn":[4.216356207],"iteration":380,"passed_time":0.3270931808,"remaining_time":0.5314191048},
{"learn":[4.214326494],"iteration":381,"passed_time":0.3275369564,"remaining_time":0.5298896311},
{"learn":[4.212901398],"iteration":382,"passed_time":0.327974448,"remaining_time":0.5283557034},
{"learn":[4.211331091],"iteration":383,"passed_time":0.3284123414,"remaining_time":0.5268281309},
{"learn":[4.208624791],"iteration":384,"passed_time":0.3288576568,"remaining_time":0.5253180751},
{"learn":[4.204659106],"iteration":385,"passed_time":0.3292973287,"remaining_time":0.5238045591},
{"learn":[4.202968852],"iteration":386,"passed_time":0.3297309716,"remaining_time":0.5222870428},
{"learn":[4.197261935],"iteration":387,"passed_time":0.330174736,"remaining_time":0.5207910784},
{"learn":[4.196934403],"iteration":388,"passed_time":0.3306358993,"remaining_time":0.5193278521},
{"learn":[4.192479929],"iteration":389,"passed_time":0.3311219579,"remaining_time":0.5179087035},
{"learn":[4.190243116],"iteration":390,"passed_time":0.3315790145,"remaining_time":0.5164491556},
{"learn":[4.185852431],"iteration":391,"passed_time":0.3320473669,"remaining_time":0.5150122425},
{"learn":[4.180967944],"iteration":392,"passed_time":0.332511474,"remaining_time":0.5135737015},
{"learn":[4.178283162],"iteration":393,"passed_time":0.3329685097,"remaining_time":0.5121292306},
{"learn":[4.176341157],"iteration":394,"passed_time":0.3334731325,"remaining_time":0.510762646},
{"learn":[4.176041504],"iteration":395,"passed_time":0.3341432696,"remaining_time":0.5096528657},
{"learn":[4.175564513],"iteration":396,"passed_time":0.3346862938,"remaining_time":0.5083522297},
{"learn":[4.170830274],"iteration":397,"passed_time":0.3351978679,"remaining_time":0.5070078303},
{"learn":[4.167804808],"iteration":398,"passed_time":0.3356721138,"remaining_time":0.5056113794},
{"learn":[4.165860548],"iteration":399,"passed_time":0.3361248218,"remaining_time":0.5041872327},
{"learn":[4.160950571],"iteration":400,"passed_time":0.3365806909,"remaining_time":0.502772653},
{"learn":[4.158544115],"iteration":401,"passed_time":0.3370291971,"remaining_time":0.5013518901},
{"learn":[4.154448767],"iteration":402,"passed_time":0.3374851018,"remaining_time":0.4999469126},
{"learn":[4.15197457],"iteration":403,"passed_time":0.3379792269,"remaining_time":0.498603018},
{"learn":[4.149562679],"iteration":404,"passed_time":0.3384487276,"remaining_time":0.4972271431},
{"learn":[4.149327961],"iteration":405,"passed_time":0.3389051098,"remaining_time":0.4958365399},
{"learn":[4.147444889],"iteration":406,"passed_time":0.3394205706,"remaining_time":0.4945366053},
{"learn":[4.147254809],"iteration":407,"passed_time":0.3398831379,"remaining_time":0.4931637688},
{"learn":[4.144589165],"iteration":408,"passed_time":0.3403385193,"remaining_time":0.4917849997},
{"learn":[4.141691034],"iteration":409,"passed_time":0.3407939458,"remaining_time":0.4904108},
{"learn":[4.138893468],"iteration":410,"passed_time":0.3412472518,"remaining_time":0.4890380324},
{"learn":[4.136964597],"iteration":411,"passed_time":0.3417091846,"remaining_time":0.4876820402},
{"learn":[4.133773523],"iteration":412,"passed_time":0.342164441,"remaining_time":0.4863208883},
{"learn":[4.131363444],"iteration":413,"passed_time":0.3426210297,"remaining_time":0.4849659985},
{"learn":[4.130228592],"iteration":414,"passed_time":0.3431486543,"remaining_time":0.483715573},
{"learn":[4.12884186],"iteration":415,"passed_time":0.3435884894,"remaining_time":0.4823453793},
{"learn":[4.12413494],"iteration":416,"passed_time":0.3440420792,"remaining_time":0.4809988781},
{"learn":[4.119422508],"iteration":417,"passed_time":0.3444996574,"remaining_time":0.4796622024},
{"learn":[4.117038244],"iteration":418,"passed_time":0.344958988,"remaining_time":0.4783321529},
{"learn":[4.116067631],"iteration":419,"passed_time":0.3454123184,"remaining_time":0.4769979635},
{"learn":[4.110343455],"iteration":420,"passed_time":0.3458722158,"remaining_time":0.4756769904},
{"learn":[4.105604544],"iteration":421,"passed_time":0.3463198027,"remaining_time":0.4743432369},
{"learn":[4.103390131],"iteration":422,"passed_time":0.3467876803,"remaining_time":0.4730413512},
{"learn":[4.096724402],"iteration":423,"passed_time":0.3472379042,"remaining_time":0.471719417},
{"learn":[4.093431279],"iteration":424,"passed_time":0.3476915964,"remaining_time":0.4704062775},
{"learn":[4.091412744],"iteration":425,"passed_time":0.3481971328,"remaining_time":0.4691670288},
{"learn":[4.091192901],"iteration":426,"passed_time":0.348665099,"remaining_time":0.4678808002},
{"learn":[4.088994581],"iteration":427,"passed_time":0.3493209882,"remaining_time":0.466849545},
{"learn":[4.087845355],"iteration":428,"passed_time":0.34983593,"remaining_time":0.4656324383},
{"learn":[4.083650279],"iteration":429,"passed_time":0.3502961624,"remaining_time":0.4643460758},
{"learn":[4.079840652],"iteration":430,"passed_time":0.3507506732,"remaining_time":0.4630559932},
{"learn":[4.075707828],"iteration":431,"passed_time":0.3512081299,"remaining_time":0.4617736523},
{"learn":[4.071345409],"iteration":432,"passed_time":0.35165494,"remaining_time":0.4604811801},
{"learn":[4.067460475],"iteration":433,"passed_time":0.3521173163,"remaining_time":0.4592129056},
{"learn":[4.064914749],"iteration":434,"passed_time":0.3525730093,"remaining_time":0.4579396558},
{"learn":[4.063823175],"iteration":435,"passed_time":0.3530505822,"remaining_time":0.4566984595},
{"learn":[4.058898471],"iteration":436,"passed_time":0.3535190977,"remaining_time":0.4554490893},
{"learn":[4.054120355],"iteration":437,"passed_time":0.3539687582,"remaining_time":0.4541790916},
{"learn":[4.052715901],"iteration":438,"passed_time":0.354412093,"remaining_time":0.4529047475},
{"learn":[4.052114167],"iteration":439,"passed_time":0.3548420748,"remaining_time":0.4516171861},
{"learn":[4.051377267],"iteration":440,"passed_time":0.355283539,"remaining_time":0.4503480687},
{"learn":[4.049275336],"iteration":441,"passed_time":0.3557246682,"remaining_time":0.4490822734},
{"learn":[4.047099198],"iteration":442,"passed_time":0.3561697432,"remaining_time":0.4478251625},
{"learn":[4.044348685],"iteration":443,"passed_time":0.3566167781,"remaining_time":0.4465741636},
{"learn":[4.042822379],"iteration":444,"passed_time":0.3570657599,"remaining_time":0.4453292061},
{"learn":[4.041258611],"iteration":445,"passed_time":0.3575134041,"remaining_time":0.4440861567},
{"learn":[4.040044254],"iteration":446,"passed_time":0.3579600805,"remaining_time":0.4428454688},
{"learn":[4.036860137],"iteration":447,"passed_time":0.3584135706,"remaining_time":0.4416167209},
{"learn":[4.036372284],"iteration":448,"passed_time":0.3588715133,"remaining_time":0.4403968905},
{"learn":[4.03368231],"iteration":449,"passed_time":0.3593289639,"remaining_time":0.4391798448},
{"learn":[4.032439519],"iteration":450,"passed_time":0.3597713682,"remaining_time":0.4379478517},
{"learn":[4.032008634],"iteration":451,"passed_time":0.3602105644,"remaining_time":0.436715463},
{"learn":[4.030034932],"iteration":452,"passed_time":0.3606506755,"remaining_time":0.435487681},
{"learn":[4.028173412],"iteration":453,"passed_time":0.3610906555,"remaining_time":0.4342632112},
{"learn":[4.023806097],"iteration":454,"passed_time":0.3615496302,"remaining_time":0.4330649417},
{"learn":[4.020239186],"iteration":455,"passed_time":0.3619976711,"remaining_time":0.4318568708},
{"learn":[4.017384838],"iteration":456,"passed_time":0.3624385955,"remaining_time":0.4306436703},
{"learn":[4.016468229],"iteration":457,"passed_time":0.3628855852,"remaining_time":0.4294410201},
{"learn":[4.014530169],"iteration":458,"passed_time":0.3633329482,"remaining_time":0.4282421024},
{"learn":[4.012884822],"iteration":459,"passed_time":0.3639334767,"remaining_time":0.4272262553},
{"learn":[4.008924707],"iteration":460,"passed_time":0.3644556192,"remaining_time":0.4261205613},
{"learn":[4.008286778],"iteration":461,"passed_time":0.3649359149,"remaining_time":0.4249686628},
{"learn":[4.006444202],"iteration":462,"passed_time":0.3654244781,"remaining_time":0.4238292543},
{"learn":[4.003284363],"iteration":463,"passed_time":0.3659255592,"remaining_time":0.4227071115},
{"learn":[3.999811484],"iteration":464,"passed_time":0.3663946129,"remaining_time":0.4215507912},
{"learn":[3.997483319],"iteration":465,"passed_time":0.3668800513,"remaining_time":0.4204161962},
{"learn":[3.99708333],"iteration":466,"passed_time":0.3673466139,"remaining_time":0.4192628377},
{"learn":[3.995860263],"iteration":467,"passed_time":0.3678869119,"remaining_time":0.4181962332},
{"learn":[3.994131111],"iteration":468,"passed_time":0.3684400467,"remaining_time":0.4171464069},
{"learn":[3.993125499],"iteration":469,"passed_time":0.3689141768,"remaining_time":0.4160096036},
{"learn":[3.992954084],"iteration":470,"passed_time":0.369358652,"remaining_time":0.4148423077},
{"learn":[3.990635743],"iteration":471,"passed_time":0.3698063596,"remaining_time":0.4136816904},
{"learn":[3.986678254],"iteration":472,"passed_time":0.3702753751,"remaining_time":0.4125478281},
{"learn":[3.986393291],"iteration":473,"passed_time":0.3707087464,"remaining_time":0.4113772164},
{"learn":[3.986152671],"iteration":474,"passed_time":0.3711515968,"remaining_time":0.4102201859},
{"learn":[3.985596662],"iteration":475,"passed_time":0.3715844741,"remaining_time":0.4090551774},
{"learn":[3.983853457],"iteration":476,"passed_time":0.3720163134,"remaining_time":0.4078921004},
{"learn":[3.983263928],"iteration":477,"passed_time":0.3724506524,"remaining_time":0.4067348129},
{"learn":[3.980067202],"iteration":478,"passed_time":0.3728961284,"remaining_time":0.4055926574},
{"learn":[3.978115407],"iteration":479,"passed_time":0.373368779,"remaining_time":0.4044828439},
{"learn":[3.972661644],"iteration":480,"passed_time":0.3738108647,"remaining_time":0.4033427002},
{"learn":[3.969938254],"iteration":481,"passed_time":0.3742558356,"remaining_time":0.4022085536},
{"learn":[3.968211434],"iteration":482,"passed_time":0.3746849555,"remaining_time":0.401060294},
{"learn":[3.966113368],"iteration":483,"passed_time":0.3751429434,"remaining_time":0.3999457826},
{"learn":[3.962246044],"iteration":484,"passed_time":0.3755897478,"remaining_time":0.3988221033},
{"learn":[3.961319703],"iteration":485,"passed_time":0.3760339722,"remaining_time":0.3976984809},
{"learn":[3.96078191],"iteration":486,"passed_time":0.3764564252,"remaining_time":0.3965547148},
{"learn":[3.958913633],"iteration":487,"passed_time":0.3768926477,"remaining_time":0.3954283517},
{"learn":[3.957428286],"iteration":488,"passed_time":0.3773342344,"remaining_time":0.3943104167},
{"learn":[3.952641965],"iteration":489,"passed_time":0.3777629828,"remaining_time":0.39318188},
{"learn":[3.951486786],"iteration":490,"passed_time":0.3782075708,"remaining_time":0.3920726142},
{"learn":[3.94938344],"iteration":491,"passed_time":0.3787176902,"remaining_time":0.3910337126},
{"learn":[3.947297924],"iteration":492,"passed_time":0.3791601916,"remaining_time":0.3899274182},
{"learn":[3.946284886],"iteration":493,"passed_time":0.3797242678,"remaining_time":0.388948339},
{"learn":[3.943288204],"iteration":494,"passed_time":0.3801767449,"remaining_time":0.3878570831},
{"learn":[3.943076488],"iteration":495,"passed_time":0.3806143562,"remaining_time":0.3867532974},
{"learn":[3.942347078],"iteration":496,"passed_time":0.3810665863,"remaining_time":0.3856669878},
{"learn":[3.940251541],"iteration":497,"passed_time":0.3815897743,"remaining_time":0.3846547524},
{"learn":[3.939011019],"iteration":498,"passed_time":0.3820732737,"remaining_time":0.3836046295},
{"learn":[3.938760512],"iteration":499,"passed_time":0.3825165008,"remaining_time":0.3825165008},
{"learn":[3.934522727],"iteration":500,"passed_time":0.3829580015,"remaining_time":0.381429227},
{"learn":[3.930091193],"iteration":501,"passed_time":0.3833932649,"remaining_time":0.3803383385},
{"learn":[3.927671752],"iteration":502,"passed_time":0.3838335479,"remaining_time":0.3792550165},
{"learn":[3.927280041],"iteration":503,"passed_time":0.3842853722,"remaining_time":0.3781856044},
{"learn":[3.925987561],"iteration":504,"passed_time":0.3848235853,"remaining_time":0.3772033163},
{"learn":[3.921645957],"iteration":505,"passed_time":0.3853280563,"remaining_time":0.3761898415},
{"learn":[3.920333743],"iteration":506,"passed_time":0.3857956032,"remaining_time":0.3751424702},
{"learn":[3.918659461],"iteration":507,"passed_time":0.3862762495,"remaining_time":0.3741100685},
{"learn":[3.916124385],"iteration":508,"passed_time":0.3867544821,"remaining_time":0.3730775063},
{"learn":[3.913849268],"iteration":509,"passed_time":0.3872375084,"remaining_time":0.3720517238},
{"learn":[3.912826119],"iteration":510,"passed_time":0.3877164319,"remaining_time":0.3710241393},
{"learn":[3.910034145],"iteration":511,"passed_time":0.388205909,"remaining_time":0.370008757},
{"learn":[3.90792379],"iteration":512,"passed_time":0.3887023109,"remaining_time":0.3690019988},
{"learn":[3.907823851],"iteration":513,"passed_time":0.3891461629,"remaining_time":0.3679475392},
{"learn":[3.904527401],"iteration":514,"passed_time":0.3895911086,"remaining_time":0.3668964809},
{"learn":[3.903378283],"iteration":515,"passed_time":0.3900395218,"remaining_time":0.3658510243},
{"learn":[3.902170135],"iteration":516,"passed_time":0.3904855429,"remaining_time":0.3648056426},
{"learn":[3.899435429],"iteration":517,"passed_time":0.390939723,"remaining_time":0.363770167},
{"learn":[3.897497505],"iteration":518,"passed_time":0.3913924553,"remaining_time":0.3627355896},
{"learn":[3.896426119],"iteration":519,"passed_time":0.391843318,"remaining_time":0.3617015243},
{"learn":[3.896044669],"iteration":520,"passed_time":0.3922950208,"remaining_time":0.3606704702},
{"learn":[3.892795942],"iteration":521,"passed_time":0.392753191,"remaining_time":0.359647558},
{"learn":[3.892413888],"iteration":522,"passed_time":0.3931997676,"remaining_time":0.3586162316},
{"learn":[3.891738985],"iteration":523,"passed_time":0.3937138288,"remaining_time":0.3576484399},
{"learn":[3.88822057],"iteration":524,"passed_time":0.3942899989,"remaining_time":0.3567385704},
{"learn":[3.883837053],"iteration":525,"passed_time":0.394806043,"remaining_time":0.3557757878},
{"learn":[3.881769742],"iteration":526,"passed_time":0.3953907457,"remaining_time":0.3548763239},
{"learn":[3.880356898],"iteration":527,"passed_time":0.3960157914,"remaining_time":0.3540141166},
{"learn":[3.879250273],"iteration":528,"passed_time":0.3964870324,"remaining_time":0.3530158644},
{"learn":[3.877174493],"iteration":529,"passed_time":0.3969833978,"remaining_time":0.3520418811},
{"learn":[3.875854201],"iteration":530,"passed_time":0.397442764,"remaining_time":0.3510370176},
{"learn":[3.873189396],"iteration":531,"passed_time":0.3978983259,"remaining_time":0.3500308581},
{"learn":[3.871583368],"iteration":532,"passed_time":0.3983919802,"remaining_time":0.3490601402},
{"learn":[3.869622679],"iteration":533,"passed_time":0.3988498492,"remaining_time":0.3480599807},
{"learn":[3.866860164],"iteration":534,"passed_time":0.3993033687,"remaining_time":0.3470580681},
{"learn":[3.864498444],"iteration":535,"passed_time":0.3997961398,"remaining_time":0.3460921807},
{"learn":[3.861416322],"iteration":536,"passed_time":0.4002482255,"remaining_time":0.3450929765},
{"learn":[3.860265769],"iteration":537,"passed_time":0.400703816,"remaining_time":0.344098816},
{"learn":[3.859328725],"iteration":538,"passed_time":0.401153473,"remaining_time":0.343101579},
{"learn":[3.858521278],"iteration":539,"passed_time":0.4016069691,"remaining_time":0.3421096404},
{"learn":[3.85599111],"iteration":540,"passed_time":0.4020647001,"remaining_time":0.3411232853},
{"learn":[3.852379816],"iteration":541,"passed_time":0.4025277066,"remaining_time":0.3401433388},
{"learn":[3.851327537],"iteration":542,"passed_time":0.4029840045,"remaining_time":0.3391596502},
{"learn":[3.847854898],"iteration":543,"passed_time":0.4034554608,"remaining_time":0.3381906068},
{"learn":[3.847083414],"iteration":544,"passed_time":0.4039016963,"remaining_time":0.3372023336},
{"learn":[3.845397429],"iteration":545,"passed_time":0.4043475056,"remaining_time":0.3362156915},
{"learn":[3.841933528],"iteration":546,"passed_time":0.4047981053,"remaining_time":0.335234994},
{"learn":[3.840996474],"iteration":547,"passed_time":0.4052549171,"remaining_time":0.3342613549},
{"learn":[3.838355966],"iteration":548,"passed_time":0.4057155063,"remaining_time":0.3332927019},
{"learn":[3.83342799],"iteration":549,"passed_time":0.4061747987,"remaining_time":0.3323248353},
{"learn":[3.828161535],"iteration":550,"passed_time":0.4066227615,"remaining_time":0.3313495824},
{"learn":[3.823502399],"iteration":551,"passed_time":0.4070582202,"remaining_time":0.3303660918},
{"learn":[3.820068862],"iteration":552,"passed_time":0.4075062133,"remaining_time":0.3293947149},
{"learn":[3.817951642],"iteration":553,"passed_time":0.4079497347,"remaining_time":0.3284216276},
{"learn":[3.815785958],"iteration":554,"passed_time":0.4084670369,"remaining_time":0.3275096062},
{"learn":[3.81503012],"iteration":555,"passed_time":0.4090358296,"remaining_time":0.3266401229},
{"learn":[3.813529315],"iteration":556,"passed_time":0.4095957594,"remaining_time":0.3257646704},
{"learn":[3.808881326],"iteration":557,"passed_time":0.4100496427,"remaining_time":0.3248063478},
{"learn":[3.808740434],"iteration":558,"passed_time":0.4105045215,"remaining_time":0.3238506153},
{"learn":[3.80714352],"iteration":559,"passed_time":0.4109468806,"remaining_time":0.3228868347},
{"learn":[3.80573346],"iteration":560,"passed_time":0.4113879464,"remaining_time":0.321923901},
{"learn":[3.803370052],"iteration":561,"passed_time":0.4118355455,"remaining_time":0.3209679162},
{"learn":[3.803215211],"iteration":562,"passed_time":0.4122694853,"remaining_time":0.3200031351},
{"learn":[3.801309667],"iteration":563,"passed_time":0.4127215683,"remaining_time":0.319054262},
{"learn":[3.800003847],"iteration":564,"passed_time":0.4132129146,"remaining_time":0.3181373768},
{"learn":[3.798026138],"iteration":565,"passed_time":0.413665094,"remaining_time":0.3171919626},
{"learn":[3.794745847],"iteration":566,"passed_time":0.4141233918,"remaining_time":0.3162529606},
{"learn":[3.794312041],"iteration":567,"passed_time":0.4145946406,"remaining_time":0.3153255013},
{"learn":[3.792205926],"iteration":568,"passed_time":0.4151159346,"remaining_time":0.3144375533},
{"learn":[3.788991061],"iteration":569,"passed_time":0.4156137274,"remaining_time":0.3135331628},
{"learn":[3.787391572],"iteration":570,"passed_time":0.4161148984,"remaining_time":0.3126327345},
{"learn":[3.7826445],"iteration":571,"passed_time":0.4166481427,"remaining_time":0.3117577012},
{"learn":[3.781700331],"iteration":572,"passed_time":0.4171311843,"remaining_time":0.3108464497},
{"learn":[3.780045374],"iteration":573,"passed_time":0.4176785931,"remaining_time":0.3099844611},
{"learn":[3.775462644],"iteration":574,"passed_time":0.4181851294,"remaining_time":0.3090933565},
{"learn":[3.773711943],"iteration":575,"passed_time":0.4186943052,"remaining_time":0.3082055303},
{"learn":[3.772415806],"iteration":576,"passed_time":0.4192305185,"remaining_time":0.3073388377},
{"learn":[3.770170875],"iteration":577,"passed_time":0.4196847472,"remaining_time":0.3064134313},
{"learn":[3.765166479],"iteration":578,"passed_time":0.4201864775,"remaining_time":0.3055241918},
{"learn":[3.763976102],"iteration":579,"passed_time":0.420692855,"remaining_time":0.3046396536},
{"learn":[3.760761708],"iteration":580,"passed_time":0.4211862641,"remaining_time":0.3037470648},
{"learn":[3.758155662],"iteration":581,"passed_time":0.4216520689,"remaining_time":0.302836022},
{"learn":[3.756844548],"iteration":582,"passed_time":0.4221346335,"remaining_time":0.3019384943},
{"learn":[3.753098923],"iteration":583,"passed_time":0.4225914609,"remaining_time":0.3010240544},
{"learn":[3.751618946],"iteration":584,"passed_time":0.4232558741,"remaining_time":0.3002584406},
{"learn":[3.751398464],"iteration":585,"passed_time":0.423860029,"remaining_time":0.2994506007},
{"learn":[3.749920103],"iteration":586,"passed_time":0.42438181,"remaining_time":0.2985854983},
{"learn":[3.748237465],"iteration":587,"passed_time":0.4248717393,"remaining_time":0.2976992459},
{"learn":[3.746021536],"iteration":588,"passed_time":0.4253648845,"remaining_time":0.2968165833},
{"learn":[3.74417648],"iteration":589,"passed_time":0.4258492133,"remaining_time":0.2959291143},
{"learn":[3.738788389],"iteration":590,"passed_time":0.4263456199,"remaining_time":0.2950513681},
{"learn":[3.736021611],"iteration":591,"passed_time":0.4267993582,"remaining_time":0.2941455036},
{"learn":[3.734546151],"iteration":592,"passed_time":0.4272594474,"remaining_time":0.2932455229},
{"learn":[3.733527479],"iteration":593,"passed_time":0.4277065197,"remaining_time":0.2923381262},
{"learn":[3.733026392],"iteration":594,"passed_time":0.4281373278,"remaining_time":0.2914212063},
{"learn":[3.730314752],"iteration":595,"passed_time":0.428592736,"remaining_time":0.2905225929},
{"learn":[3.727342596],"iteration":596,"passed_time":0.4290371731,"remaining_time":0.2896180582},
{"learn":[3.725459604],"iteration":597,"passed_time":0.4294811406,"remaining_time":0.2887147467},
{"learn":[3.723158842],"iteration":598,"passed_time":0.4299224069,"remaining_time":0.2878111605},
{"learn":[3.722362756],"iteration":599,"passed_time":0.4303692213,"remaining_time":0.2869128142},
{"learn":[3.721443615],"iteration":600,"passed_time":0.4308177509,"remaining_time":0.2860171092},
{"learn":[3.720743486],"iteration":601,"passed_time":0.4312600536,"remaining_time":0.285118773},
{"learn":[3.720215334],"iteration":602,"passed_time":0.4317033354,"remaining_time":0.2842225939},
{"learn":[3.719436563],"iteration":603,"passed_time":0.4321389616,"remaining_time":0.2833228954},
{"learn":[3.715046574],"iteration":604,"passed_time":0.4325777716,"remaining_time":0.2824268095},
{"learn":[3.71443396],"iteration":605,"passed_time":0.4330549747,"remaining_time":0.2815571948},
{"learn":[3.712938941],"iteration":606,"passed_time":0.4334969042,"remaining_time":0.2806660351},
{"learn":[3.712814764],"iteration":607,"passed_time":0.4339395575,"remaining_time":0.27977682},
{"learn":[3.71235348],"iteration":608,"passed_time":0.4343882346,"remaining_time":0.2788929388},
{"learn":[3.711223749],"iteration":609,"passed_time":0.4348211571,"remaining_time":0.2780004119},
{"learn":[3.710755648],"iteration":610,"passed_time":0.435257226,"remaining_time":0.2771113927},
{"learn":[3.708668039],"iteration":611,"passed_time":0.4357169473,"remaining_time":0.2762388489},
{"learn":[3.705623591],"iteration":612,"passed_time":0.4361555003,"remaining_time":0.2753542881},
{"learn":[3.704045802],"iteration":613,"passed_time":0.4366024675,"remaining_time":0.2744764698},
{"learn":[3.699915209],"iteration":614,"passed_time":0.4370946666,"remaining_time":0.2736283685},
{"learn":[3.696182221],"iteration":615,"passed_time":0.4376194556,"remaining_time":0.2728017386},
{"learn":[3.694263278],"iteration":616,"passed_time":0.4380628823,"remaining_time":0.2719255817},
{"learn":[3.693810229],"iteration":617,"passed_time":0.4385785068,"remaining_time":0.2710954524},
{"learn":[3.690900932],"iteration":618,"passed_time":0.4391264416,"remaining_time":0.2702862266},
{"learn":[3.688020895],"iteration":619,"passed_time":0.4395849555,"remaining_time":0.2694230372},
{"learn":[3.685491894],"iteration":620,"passed_time":0.4400396772,"remaining_time":0.2685588368},
{"learn":[3.684328128],"iteration":621,"passed_time":0.4404759414,"remaining_time":0.2676847361},
{"learn":[3.680640153],"iteration":622,"passed_time":0.4409177771,"remaining_time":0.2668154125},
{"learn":[3.678932783],"iteration":623,"passed_time":0.4413674055,"remaining_time":0.2659521546},
{"learn":[3.674167041],"iteration":624,"passed_time":0.4418150072,"remaining_time":0.2650890043},
{"learn":[3.672200976],"iteration":625,"passed_time":0.4422575929,"remaining_time":0.2642241849},
{"learn":[3.670606604],"iteration":626,"passed_time":0.4427120359,"remaining_time":0.2633677662},
{"learn":[3.665506042],"iteration":627,"passed_time":0.4431577177,"remaining_time":0.2625074379},
{"learn":[3.664214007],"iteration":628,"passed_time":0.4436023543,"remaining_time":0.2616478115},
{"learn":[3.66261643],"iteration":629,"passed_time":0.4440498866,"remaining_time":0.2607912032},
{"learn":[3.662118449],"iteration":630,"passed_time":0.4445535538,"remaining_time":0.2599687185},
{"learn":[3.660871366],"iteration":631,"passed_time":0.4450833311,"remaining_time":0.2591624459},
{"learn":[3.656695243],"iteration":632,"passed_time":0.4455776259,"remaining_time":0.258336475},
{"learn":[3.654497801],"iteration":633,"passed_time":0.4460568167,"remaining_time":0.2575028311},
{"learn":[3.654189134],"iteration":634,"passed_time":0.4465645261,"remaining_time":0.2566866961},
{"learn":[3.653957699],"iteration":635,"passed_time":0.4470716452,"remaining_time":0.2558711932},
{"learn":[3.651920725],"iteration":636,"passed_time":0.4475607344,"remaining_time":0.255046384},
{"learn":[3.65106705],"iteration":637,"passed_time":0.4480772676,"remaining_time":0.2542381989},
{"learn":[3.650612844],"iteration":638,"passed_time":0.4486410113,"remaining_time":0.2534575979},
{"learn":[3.649884732],"iteration":639,"passed_time":0.4491196691,"remaining_time":0.2526298139},
{"learn":[3.646276182],"iteration":640,"passed_time":0.4496354385,"remaining_time":0.251823904},
{"learn":[3.645808194],"iteration":641,"passed_time":0.4501716969,"remaining_time":0.2510303232},
{"learn":[3.645042989],"iteration":642,"passed_time":0.4508245778,"remaining_time":0.2503022928},
{"learn":[3.639864499],"iteration":643,"passed_time":0.4513628316,"remaining_time":0.2495111305},
{"learn":[3.637318478],"iteration":644,"passed_time":0.4519149761,"remaining_time":0.2487283977},
{"learn":[3.636344905],"iteration":645,"passed_time":0.4524470435,"remaining_time":0.2479353768},
{"learn":[3.634754643],"iteration":646,"passed_time":0.4529573803,"remaining_time":0.2471313064},
{"learn":[3.630724975],"iteration":647,"passed_time":0.4535306721,"remaining_time":0.2463623404},
{"learn":[3.629408252],"iteration":648,"passed_time":0.4541214298,"remaining_time":0.2456034235},
{"learn":[3.62790646],"iteration":649,"passed_time":0.4546945328,"remaining_time":0.2448355177},
{"learn":[3.627388973],"iteration":650,"passed_time":0.455291142,"remaining_time":0.2440808119},
{"learn":[3.625163557],"iteration":651,"passed_time":0.4558950104,"remaining_time":0.2433304657},
{"learn":[3.623701985],"iteration":652,"passed_time":0.4564850971,"remaining_time":0.2425732446},
{"learn":[3.622342639],"iteration":653,"passed_time":0.4570577037,"remaining_time":0.2418072867},
{"learn":[3.621130639],"iteration":654,"passed_time":0.4576886938,"remaining_time":0.2410726708},
{"learn":[3.619125665],"iteration":655,"passed_time":0.4582738087,"remaining_time":0.2403143143},
{"learn":[3.618878783],"iteration":656,"passed_time":0.4588824046,"remaining_time":0.239568744},
{"learn":[3.616207429],"iteration":657,"passed_time":0.4594087013,"remaining_time":0.2387808143},
{"learn":[3.61206486],"iteration":658,"passed_time":0.4599132638,"remaining_time":0.2379824324},
{"learn":[3.611955873],"iteration":659,"passed_time":0.460459283,"remaining_time":0.2372062973},
{"learn":[3.610713743],"iteration":660,"passed_time":0.4610287684,"remaining_time":0.2364428933},
{"learn":[3.610044025],"iteration":661,"passed_time":0.4615746929,"remaining_time":0.2356680456},
{"learn":[3.607342669],"iteration":662,"passed_time":0.4620844542,"remaining_time":0.2348755069},
{"learn":[3.602510618],"iteration":663,"passed_time":0.4626094303,"remaining_time":0.2340915189},
{"learn":[3.600492392],"iteration":664,"passed_time":0.4631075264,"remaining_time":0.2332947689},
{"learn":[3.597171065],"iteration":665,"passed_time":0.4636522336,"remaining_time":0.2325222913},
{"learn":[3.594358798],"iteration":666,"passed_time":0.4641756985,"remaining_time":0.2317398915},
{"learn":[3.593945251],"iteration":667,"passed_time":0.4646977703,"remaining_time":0.2309575745},
{"learn":[3.593607748],"iteration":668,"passed_time":0.4654063777,"remaining_time":0.2302683274},
{"learn":[3.592238714],"iteration":669,"passed_time":0.4659333492,"remaining_time":0.2294895601},
{"learn":[3.590144654],"iteration":670,"passed_time":0.4665170763,"remaining_time":0.2287393712},
{"learn":[3.587151536],"iteration":671,"passed_time":0.4671864465,"remaining_time":0.2280314798},
{"learn":[3.586070865],"iteration":672,"passed_time":0.4679484487,"remaining_time":0.2273687113},
{"learn":[3.585102746],"iteration":673,"passed_time":0.4688560133,"remaining_time":0.2267760539},
{"learn":[3.584362847],"iteration":674,"passed_time":0.4695900849,"remaining_time":0.2260989298},
{"learn":[3.581407561],"iteration":675,"passed_time":0.4702271048,"remaining_time":0.2253751212},
{"learn":[3.57919422],"iteration":676,"passed_time":0.4710067443,"remaining_time":0.2247196136},
{"learn":[3.577632204],"iteration":677,"passed_time":0.4715811727,"remaining_time":0.2239662797},
{"learn":[3.573911195],"iteration":678,"passed_time":0.4722246573,"remaining_time":0.2232461193},
{"learn":[3.573408216],"iteration":679,"passed_time":0.4727792881,"remaining_time":0.2224843709},
{"learn":[3.571076482],"iteration":680,"passed_time":0.4733860365,"remaining_time":0.2217476441},
{"learn":[3.568177107],"iteration":681,"passed_time":0.4738821762,"remaining_time":0.2209597244},
{"learn":[3.564824621],"iteration":682,"passed_time":0.4743657867,"remaining_time":0.2201668439},
{"learn":[3.562475026],"iteration":683,"passed_time":0.4749836877,"remaining_time":0.2194369083},
{"learn":[3.561226889],"iteration":684,"passed_time":0.4754914444,"remaining_time":0.2186566496},
{"learn":[3.559383467],"iteration":685,"passed_time":0.4760854092,"remaining_time":0.217916645},
{"learn":[3.555209766],"iteration":686,"passed_time":0.4766305218,"remaining_time":0.2171548083},
{"learn":[3.55345383],"iteration":687,"passed_time":0.4771437199,"remaining_time":0.2163791288},
{"learn":[3.552300968],"iteration":688,"passed_time":0.4777056139,"remaining_time":0.2156261915},
{"learn":[3.551253986],"iteration":689,"passed_time":0.4782731177,"remaining_time":0.2148763282},
{"learn":[3.549807725],"iteration":690,"passed_time":0.4788598358,"remaining_time":0.214135585},
{"learn":[3.547992926],"iteration":691,"passed_time":0.4795175421,"remaining_time":0.2134268829},
{"learn":[3.545438607],"iteration":692,"passed_time":0.4800761474,"remaining_time":0.212674426},
{"learn":[3.543313763],"iteration":693,"passed_time":0.4805992099,"remaining_time":0.2119068563},
{"learn":[3.542962896],"iteration":694,"passed_time":0.4811538842,"remaining_time":0.2111538628},
{"learn":[3.539800465],"iteration":695,"passed_time":0.481746994,"remaining_time":0.2104182273},
{"learn":[3.53953187],"iteration":696,"passed_time":0.4822407408,"remaining_time":0.2096398055},
{"learn":[3.536332425],"iteration":697,"passed_time":0.4827744326,"remaining_time":0.2088794823},
{"learn":[3.534993327],"iteration":698,"passed_time":0.483461236,"remaining_time":0.2081857397},
{"learn":[3.531637011],"iteration":699,"passed_time":0.4840303472,"remaining_time":0.2074415774},
{"learn":[3.531040284],"iteration":700,"passed_time":0.4845894759,"remaining_time":0.2066936566},
{"learn":[3.529973872],"iteration":701,"passed_time":0.4851367602,"remaining_time":0.2059412458},
{"learn":[3.527325183],"iteration":702,"passed_time":0.4856996737,"remaining_time":0.2051960214},
{"learn":[3.527200815],"iteration":703,"passed_time":0.4862065949,"remaining_time":0.2044277729},
{"learn":[3.523459911],"iteration":704,"passed_time":0.4867446379,"remaining_time":0.2036732882},
{"learn":[3.522729934],"iteration":705,"passed_time":0.4872230206,"remaining_time":0.2028945723},
{"learn":[3.522260582],"iteration":706,"passed_time":0.4877210421,"remaining_time":0.2021248449},
{"learn":[3.518641591],"iteration":707,"passed_time":0.4882357413,"remaining_time":0.2013627633},
{"learn":[3.516856405],"iteration":708,"passed_time":0.4887329308,"remaining_time":0.200594193},
{"learn":[3.515083413],"iteration":709,"passed_time":0.489253379,"remaining_time":0.1998358872},
{"learn":[3.514671214],"iteration":710,"passed_time":0.4897300284,"remaining_time":0.1990604475},
{"learn":[3.512617621],"iteration":711,"passed_time":0.4901773506,"remaining_time":0.1982739845},
{"learn":[3.510747971],"iteration":712,"passed_time":0.4906381637,"remaining_time":0.1974939032},
{"learn":[3.508149266],"iteration":713,"passed_time":0.4911663252,"remaining_time":0.1967416933},
{"learn":[3.504557165],"iteration":714,"passed_time":0.4916286981,"remaining_time":0.1959638866},
{"learn":[3.501367208],"iteration":715,"passed_time":0.4921617575,"remaining_time":0.1952149988},
{"learn":[3.497593362],"iteration":716,"passed_time":0.4926271605,"remaining_time":0.194440009},
{"learn":[3.496291169],"iteration":717,"passed_time":0.4931392992,"remaining_time":0.1936842373},
{"learn":[3.49330374],"iteration":718,"passed_time":0.4936136714,"remaining_time":0.1929143834},
{"learn":[3.490044385],"iteration":719,"passed_time":0.494124476,"remaining_time":0.1921595184},
{"learn":[3.488891789],"iteration":720,"passed_time":0.4945581753,"remaining_time":0.1913754936},
{"learn":[3.486869081],"iteration":721,"passed_time":0.4950290644,"remaining_time":0.1906067589},
{"learn":[3.486303638],"iteration":722,"passed_time":0.495472268,"remaining_time":0.189828241},
{"learn":[3.486035862],"iteration":723,"passed_time":0.4959839879,"remaining_time":0.1890767689},
{"learn":[3.482668951],"iteration":724,"passed_time":0.4964338489,"remaining_time":0.1883024944},
{"learn":[3.47820549],"iteration":725,"passed_time":0.4969989263,"remaining_time":0.1875725975},
{"learn":[3.474392283],"iteration":726,"passed_time":0.497484662,"remaining_time":0.18681336},
{"learn":[3.472268163],"iteration":727,"passed_time":0.4979983483,"remaining_time":0.1860653169},
{"learn":[3.471209164],"iteration":728,"passed_time":0.498502334,"remaining_time":0.1853143107},
{"learn":[3.470049971],"iteration":729,"passed_time":0.4990463122,"remaining_time":0.184578773},
{"learn":[3.469078654],"iteration":730,"passed_time":0.4995915511,"remaining_time":0.1838442233},
{"learn":[3.468643292],"iteration":731,"passed_time":0.5001465274,"remaining_time":0.1831137559},
{"learn":[3.468134848],"iteration":732,"passed_time":0.5006434986,"remaining_time":0.1823626387},
{"learn":[3.467820182],"iteration":733,"passed_time":0.5011204691,"remaining_time":0.1816049656},
{"learn":[3.465776156],"iteration":734,"passed_time":0.5016095808,"remaining_time":0.1808524339},
{"learn":[3.463037608],"iteration":735,"passed_time":0.5021314378,"remaining_time":0.1801123636},
{"learn":[3.45965637],"iteration":736,"passed_time":0.5028421383,"remaining_time":0.1794402746},
{"learn":[3.457275091],"iteration":737,"passed_time":0.5033832591,"remaining_time":0.1787078779},
{"learn":[3.455522955],"iteration":738,"passed_time":0.5039733441,"remaining_time":0.177993292},
{"learn":[3.451270508],"iteration":739,"passed_time":0.5044945032,"remaining_time":0.1772548255},
{"learn":[3.450978947],"iteration":740,"passed_time":0.5049390896,"remaining_time":0.1764901811},
{"learn":[3.450608492],"iteration":741,"passed_time":0.5054112684,"remaining_time":0.1757359936},
{"learn":[3.448122004],"iteration":742,"passed_time":0.505912514,"remaining_time":0.1749926192},
{"learn":[3.445646714],"iteration":743,"passed_time":0.5063781535,"remaining_time":0.1742376442},
{"learn":[3.44411263],"iteration":744,"passed_time":0.5068526424,"remaining_time":0.1734864749},
{"learn":[3.443264164],"iteration":745,"passed_time":0.5073628355,"remaining_time":0.1727482041},
{"learn":[3.439521363],"iteration":746,"passed_time":0.5078879144,"remaining_time":0.1720155855},
{"learn":[3.436809225],"iteration":747,"passed_time":0.5083785668,"remaining_time":0.1712719236},
{"learn":[3.435509465],"iteration":748,"passed_time":0.5088802377,"remaining_time":0.1705326297},
{"learn":[3.434450277],"iteration":749,"passed_time":0.5093707325,"remaining_time":0.1697902442},
{"learn":[3.431786753],"iteration":750,"passed_time":0.5098638669,"remaining_time":0.1690494046},
{"learn":[3.430150302],"iteration":751,"passed_time":0.5103498921,"remaining_time":0.1683068793},
{"learn":[3.42696281],"iteration":752,"passed_time":0.5108419285,"remaining_time":0.1675670071},
{"learn":[3.426870334],"iteration":753,"passed_time":0.5112576512,"remaining_time":0.1668028941},
{"learn":[3.425200309],"iteration":754,"passed_time":0.5117401763,"remaining_time":0.1660613817},
{"learn":[3.423383783],"iteration":755,"passed_time":0.5122562794,"remaining_time":0.1653313918},
{"learn":[3.422752979],"iteration":756,"passed_time":0.51271538,"remaining_time":0.1645836689},
{"learn":[3.420845924],"iteration":757,"passed_time":0.5132716296,"remaining_time":0.1638677234},
{"learn":[3.418917862],"iteration":758,"passed_time":0.5138780217,"remaining_time":0.1631681202},
{"learn":[3.417095735],"iteration":759,"passed_time":0.5143628209,"remaining_time":0.1624303645},
{"learn":[3.414391848],"iteration":760,"passed_time":0.5148552774,"remaining_time":0.1616956784},
{"learn":[3.41426711],"iteration":761,"passed_time":0.5153236692,"remaining_time":0.1609541119},
{"learn":[3.411976013],"iteration":762,"passed_time":0.5158279058,"remaining_time":0.1602243954},
{"learn":[3.408614844],"iteration":763,"passed_time":0.5162825607,"remaining_time":0.1594799533},
{"learn":[3.407906721],"iteration":764,"passed_time":0.5167740832,"remaining_time":0.1587475942},
{"learn":[3.407494015],"iteration":765,"passed_time":0.5172378084,"remaining_time":0.1580073723},
{"learn":[3.406287128],"iteration":766,"passed_time":0.5177458989,"remaining_time":0.1572813487},
{"learn":[3.404600442],"iteration":767,"passed_time":0.5182486148,"remaining_time":0.156554269},
{"learn":[3.404012662],"iteration":768,"passed_time":0.5187305957,"remaining_time":0.1558215443},
{"learn":[3.400398762],"iteration":769,"passed_time":0.5191843513,"remaining_time":0.15508104},
{"learn":[3.399737714],"iteration":770,"passed_time":0.5196790801,"remaining_time":0.1543534492},
{"learn":[3.399185251],"iteration":771,"passed_time":0.5201689795,"remaining_time":0.1536250354},
{"learn":[3.397245411],"iteration":772,"passed_time":0.5207409065,"remaining_time":0.152921327},
{"learn":[3.396229831],"iteration":773,"passed_time":0.5212586748,"remaining_time":0.1522021454},
{"learn":[3.394002836],"iteration":774,"passed_time":0.5218381046,"remaining_time":0.1515013852},
{"learn":[3.389617243],"iteration":775,"passed_time":0.5224796887,"remaining_time":0.1508188792},
{"learn":[3.385426488],"iteration":776,"passed_time":0.5230521911,"remaining_time":0.150116652},
{"learn":[3.385072258],"iteration":777,"passed_time":0.5235443755,"remaining_time":0.1493918398},
{"learn":[3.383842366],"iteration":778,"passed_time":0.5240547049,"remaining_time":0.1486727725},
{"learn":[3.380110746],"iteration":779,"passed_time":0.5245497171,"remaining_time":0.1479499202},
{"learn":[3.378595218],"iteration":780,"passed_time":0.5251042034,"remaining_time":0.1472443285},
{"learn":[3.377371219],"iteration":781,"passed_time":0.5256354579,"remaining_time":0.1465326468},
{"learn":[3.375814782],"iteration":782,"passed_time":0.5262609263,"remaining_time":0.1458475364},
{"learn":[3.374195887],"iteration":783,"passed_time":0.526927131,"remaining_time":0.1451738014},
{"learn":[3.373704309],"iteration":784,"passed_time":0.5275024036,"remaining_time":0.1444751806},
{"learn":[3.372971757],"iteration":785,"passed_time":0.5281791398,"remaining_time":0.1438044986},
{"learn":[3.371565136],"iteration":786,"passed_time":0.5289628566,"remaining_time":0.1431627553},
{"learn":[3.3700309],"iteration":787,"passed_time":0.5295484793,"remaining_time":0.1424673574},
{"learn":[3.368186663],"iteration":788,"passed_time":0.5301178805,"remaining_time":0.1417678996},
{"learn":[3.366710398],"iteration":789,"passed_time":0.5307074342,"remaining_time":0.1410741281},
{"learn":[3.364598042],"iteration":790,"passed_time":0.531282275,"remaining_time":0.1403767326},
{"learn":[3.36348442],"iteration":791,"passed_time":0.5318249703,"remaining_time":0.1396712043},
{"learn":[3.362001759],"iteration":792,"passed_time":0.5324059689,"remaining_time":0.1389760852},
{"learn":[3.361580401],"iteration":793,"passed_time":0.5329979309,"remaining_time":0.1382840979},
{"learn":[3.359543675],"iteration":794,"passed_time":0.5335814088,"remaining_time":0.1375901746},
{"learn":[3.35766119],"iteration":795,"passed_time":0.5341787527,"remaining_time":0.1369000824},
{"learn":[3.354592969],"iteration":796,"passed_time":0.5347406259,"remaining_time":0.1362011883},
{"learn":[3.350985986],"iteration":797,"passed_time":0.535356761,"remaining_time":0.1355163731},
{"learn":[3.349589624],"iteration":798,"passed_time":0.5359294401,"remaining_time":0.1348207978},
{"learn":[3.349110856],"iteration":799,"passed_time":0.5365133716,"remaining_time":0.1341283429},
{"learn":[3.345315441],"iteration":800,"passed_time":0.537054623,"remaining_time":0.1334255555},
{"learn":[3.34397474],"iteration":801,"passed_time":0.5375867585,"remaining_time":0.1327209204},
{"learn":[3.343800902],"iteration":802,"passed_time":0.5381847694,"remaining_time":0.1320328762},
{"learn":[3.342329465],"iteration":803,"passed_time":0.5387671728,"remaining_time":0.1313412511},
{"learn":[3.34220347],"iteration":804,"passed_time":0.5393356179,"remaining_time":0.1306465161},
{"learn":[3.341279219],"iteration":805,"passed_time":0.539828908,"remaining_time":0.1299340052},
{"learn":[3.337329521],"iteration":806,"passed_time":0.5404550079,"remaining_time":0.1292537999},
{"learn":[3.336708453],"iteration":807,"passed_time":0.5410803683,"remaining_time":0.1285735529},
{"learn":[3.333252703],"iteration":808,"passed_time":0.5416569736,"remaining_time":0.1278819307},
{"learn":[3.332186769],"iteration":809,"passed_time":0.5422483042,"remaining_time":0.1271940467},
{"learn":[3.330594851],"iteration":810,"passed_time":0.5429607914,"remaining_time":0.1265346357},
{"learn":[3.327867442],"iteration":811,"passed_time":0.5436055476,"remaining_time":0.1258594125},
{"learn":[3.327563111],"iteration":812,"passed_time":0.5442569971,"remaining_time":0.1251858038},
{"learn":[3.326308994],"iteration":813,"passed_time":0.5449538465,"remaining_time":0.1245226234},
{"learn":[3.326249879],"iteration":814,"passed_time":0.5455880845,"remaining_time":0.123845148},
{"learn":[3.322336238],"iteration":815,"passed_time":0.546184228,"remaining_time":0.1231591887},
{"learn":[3.320491154],"iteration":816,"passed_time":0.5468263607,"remaining_time":0.1224837503},
{"learn":[3.320434271],"iteration":817,"passed_time":0.5474247209,"remaining_time":0.1217986543},
{"learn":[3.319609638],"iteration":818,"passed_time":0.5480131698,"remaining_time":0.1211115796},
{"learn":[3.316182682],"iteration":819,"passed_time":0.5485905593,"remaining_time":0.1204223179},
{"learn":[3.313126612],"iteration":820,"passed_time":0.5492914752,"remaining_time":0.1197602607},
{"learn":[3.311222803],"iteration":821,"passed_time":0.549877886,"remaining_time":0.1190733135},
{"learn":[3.309627335],"iteration":822,"passed_time":0.5506335863,"remaining_time":0.1184230192},
{"learn":[3.307974895],"iteration":823,"passed_time":0.5513178861,"remaining_time":0.1177572184},
{"learn":[3.307321505],"iteration":824,"passed_time":0.5519376793,"remaining_time":0.1170776895},
{"learn":[3.306759087],"iteration":825,"passed_time":0.5526117565,"remaining_time":0.1164097405},
{"learn":[3.30484037],"iteration":826,"passed_time":0.5533005858,"remaining_time":0.1157448626},
{"learn":[3.30201994],"iteration":827,"passed_time":0.5538774749,"remaining_time":0.1150566735},
{"learn":[3.299302297],"iteration":828,"passed_time":0.5544756139,"remaining_time":0.1143731363},
{"learn":[3.298132671],"iteration":829,"passed_time":0.5551076264,"remaining_time":0.1136967428},
{"learn":[3.296976183],"iteration":830,"passed_time":0.5556916937,"remaining_time":0.1130107055},
{"learn":[3.293144745],"iteration":831,"passed_time":0.5562814437,"remaining_time":0.1123260607},
{"learn":[3.290284404],"iteration":832,"passed_time":0.5569051019,"remaining_time":0.1116484418},
{"learn":[3.288285745],"iteration":833,"passed_time":0.5575083515,"remaining_time":0.1109668901},
{"learn":[3.286662667],"iteration":834,"passed_time":0.5581809345,"remaining_time":0.1102992266},
{"learn":[3.285692682],"iteration":835,"passed_time":0.5588544623,"remaining_time":0.1096317366},
{"learn":[3.284565611],"iteration":836,"passed_time":0.5595157117,"remaining_time":0.1089618411},
{"learn":[3.283897383],"iteration":837,"passed_time":0.5602818368,"remaining_time":0.1083122405},
{"learn":[3.280712855],"iteration":838,"passed_time":0.5609895784,"remaining_time":0.1076511587},
{"learn":[3.280468341],"iteration":839,"passed_time":0.5615986868,"remaining_time":0.1069711784},
{"learn":[3.277814895],"iteration":840,"passed_time":0.5622705202,"remaining_time":0.1063032256},
{"learn":[3.276316385],"iteration":841,"passed_time":0.5629362875,"remaining_time":0.1056341252},
{"learn":[3.27557063],"iteration":842,"passed_time":0.5636362312,"remaining_time":0.1049713977},
{"learn":[3.27499628],"iteration":843,"passed_time":0.5642127645,"remaining_time":0.1042857716},
{"learn":[3.273569958],"iteration":844,"passed_time":0.5648604587,"remaining_time":0.1036134569},
{"learn":[3.269665595],"iteration":845,"passed_time":0.5654217894,"remaining_time":0.1029254794},
{"learn":[3.267984685],"iteration":846,"passed_time":0.566051093,"remaining_time":0.1022500794},
{"learn":[3.267702508],"iteration":847,"passed_time":0.5666566826,"remaining_time":0.1015705375},
{"learn":[3.266671924],"iteration":848,"passed_time":0.5672855678,"remaining_time":0.100895313},
{"learn":[3.265359825],"iteration":849,"passed_time":0.5678517749,"remaining_time":0.1002091367},
{"learn":[3.2618983],"iteration":850,"passed_time":0.5684501143,"remaining_time":0.09952886842},
{"learn":[3.260456253],"iteration":851,"passed_time":0.5689589403,"remaining_time":0.09883324316},
{"learn":[3.258389147],"iteration":852,"passed_time":0.5695142282,"remaining_time":0.09814606277},
{"learn":[3.258108469],"iteration":853,"passed_time":0.5700724169,"remaining_time":0.09745968719},
{"learn":[3.256424936],"iteration":854,"passed_time":0.5706129144,"remaining_time":0.09677061122},
{"learn":[3.254817983],"iteration":855,"passed_time":0.5712711303,"remaining_time":0.09610168546},
{"learn":[3.253898449],"iteration":856,"passed_time":0.5718579031,"remaining_time":0.09542086364},
{"learn":[3.253023652],"iteration":857,"passed_time":0.5724615736,"remaining_time":0.09474305764},
{"learn":[3.252845542],"iteration":858,"passed_time":0.5732398634,"remaining_time":0.094094087},
{"learn":[3.252316026],"iteration":859,"passed_time":0.5739005347,"remaining_time":0.09342566844},
{"learn":[3.24975301],"iteration":860,"passed_time":0.5745917344,"remaining_time":0.09276219638},
{"learn":[3.249151075],"iteration":861,"passed_time":0.5752202247,"remaining_time":0.09208862066},
{"learn":[3.246257135],"iteration":862,"passed_time":0.5758186857,"remaining_time":0.09141038231},
{"learn":[3.243826471],"iteration":863,"passed_time":0.5763991978,"remaining_time":0.09072950335},
{"learn":[3.243190653],"iteration":864,"passed_time":0.5770000057,"remaining_time":0.09005202401},
{"learn":[3.24008797],"iteration":865,"passed_time":0.5775824621,"remaining_time":0.08937188212},
{"learn":[3.240036811],"iteration":866,"passed_time":0.5781693451,"remaining_time":0.08869264464},
{"learn":[3.238676314],"iteration":867,"passed_time":0.5788167069,"remaining_time":0.08802281718},
{"learn":[3.237848782],"iteration":868,"passed_time":0.5794435628,"remaining_time":0.0873499502},
{"learn":[3.236405498],"iteration":869,"passed_time":0.5800450009,"remaining_time":0.08667339094},
{"learn":[3.233378068],"iteration":870,"passed_time":0.580654775,"remaining_time":0.08599823878},
{"learn":[3.233169169],"iteration":871,"passed_time":0.581216972,"remaining_time":0.08531625277},
{"learn":[3.232434885],"iteration":872,"passed_time":0.5818133264,"remaining_time":0.08463951025},
{"learn":[3.229978115],"iteration":873,"passed_time":0.5823639211,"remaining_time":0.08395635476},
{"learn":[3.229648848],"iteration":874,"passed_time":0.5828945715,"remaining_time":0.08327065307},
{"learn":[3.227208761],"iteration":875,"passed_time":0.5835233604,"remaining_time":0.08259919713},
{"learn":[3.226258869],"iteration":876,"passed_time":0.5841362384,"remaining_time":0.08192560698},
{"learn":[3.225331995],"iteration":877,"passed_time":0.5846971968,"remaining_time":0.08124494078},
{"learn":[3.221968268],"iteration":878,"passed_time":0.5853290131,"remaining_time":0.08057430101},
{"learn":[3.221166317],"iteration":879,"passed_time":0.5859672551,"remaining_time":0.0799046257},
{"learn":[3.220047503],"iteration":880,"passed_time":0.5865513693,"remaining_time":0.0792277105},
{"learn":[3.21982781],"iteration":881,"passed_time":0.5871739487,"remaining_time":0.07855615186},
{"learn":[3.216693405],"iteration":882,"passed_time":0.5877184225,"remaining_time":0.07787435496},
{"learn":[3.214798761],"iteration":883,"passed_time":0.5884571543,"remaining_time":0.07721835961},
{"learn":[3.214395085],"iteration":884,"passed_time":0.5891142209,"remaining_time":0.07655156542},
{"learn":[3.213470696],"iteration":885,"passed_time":0.5898116414,"remaining_time":0.07588998546},
{"learn":[3.211595017],"iteration":886,"passed_time":0.5905011052,"remaining_time":0.07522731103},
{"learn":[3.210965255],"iteration":887,"passed_time":0.5910190649,"remaining_time":0.07454294513},
{"learn":[3.209413583],"iteration":888,"passed_time":0.5915987221,"remaining_time":0.07386665709},
{"learn":[3.208331683],"iteration":889,"passed_time":0.5923024684,"remaining_time":0.07320592306},
{"learn":[3.207110711],"iteration":890,"passed_time":0.5929161233,"remaining_time":0.07253407119},
{"learn":[3.204519413],"iteration":891,"passed_time":0.5935281602,"remaining_time":0.07186215393},
{"learn":[3.201421296],"iteration":892,"passed_time":0.5940526801,"remaining_time":0.0711798844},
{"learn":[3.200691259],"iteration":893,"passed_time":0.594632503,"remaining_time":0.07050452497},
{"learn":[3.200485067],"iteration":894,"passed_time":0.595203102,"remaining_time":0.06982829688},
{"learn":[3.197467568],"iteration":895,"passed_time":0.5957711482,"remaining_time":0.06915200828},
{"learn":[3.195838544],"iteration":896,"passed_time":0.596319803,"remaining_time":0.06847373435},
{"learn":[3.195671746],"iteration":897,"passed_time":0.5969095851,"remaining_time":0.06780042058},
{"learn":[3.194213094],"iteration":898,"passed_time":0.5974465587,"remaining_time":0.06712135977},
{"learn":[3.192884691],"iteration":899,"passed_time":0.5980839379,"remaining_time":0.06645377088},
{"learn":[3.188364239],"iteration":900,"passed_time":0.598657725,"remaining_time":0.06577926168},
{"learn":[3.185219478],"iteration":901,"passed_time":0.5992413106,"remaining_time":0.06510604039},
{"learn":[3.184120387],"iteration":902,"passed_time":0.5997702884,"remaining_time":0.06442715169},
{"learn":[3.183725321],"iteration":903,"passed_time":0.6003156692,"remaining_time":0.06375033655},
{"learn":[3.181264554],"iteration":904,"passed_time":0.6009535197,"remaining_time":0.06308351864},
{"learn":[3.180741589],"iteration":905,"passed_time":0.6016216721,"remaining_time":0.06241990859},
{"learn":[3.179782639],"iteration":906,"passed_time":0.6021832085,"remaining_time":0.06174535655},
{"learn":[3.176377564],"iteration":907,"passed_time":0.602830494,"remaining_time":0.06107974168},
{"learn":[3.174078182],"iteration":908,"passed_time":0.6036847693,"remaining_time":0.06043488889},
{"learn":[3.171242379],"iteration":909,"passed_time":0.604317349,"remaining_time":0.0597676499},
{"learn":[3.170421012],"iteration":910,"passed_time":0.6048708128,"remaining_time":0.05909275779},
{"learn":[3.170087224],"iteration":911,"passed_time":0.6054559565,"remaining_time":0.05842118878},
{"learn":[3.167303059],"iteration":912,"passed_time":0.6060917412,"remaining_time":0.0577546347},
{"learn":[3.16705966],"iteration":913,"passed_time":0.6066677064,"remaining_time":0.05708251942},
{"learn":[3.165667683],"iteration":914,"passed_time":0.6072647469,"remaining_time":0.05641257212},
{"learn":[3.164689733],"iteration":915,"passed_time":0.6078369113,"remaining_time":0.05574050278},
{"learn":[3.163311455],"iteration":916,"passed_time":0.6083906568,"remaining_time":0.0550669842},
{"learn":[3.159425016],"iteration":917,"passed_time":0.6089778128,"remaining_time":0.05439671095},
{"learn":[3.159327058],"iteration":918,"passed_time":0.6095129688,"remaining_time":0.05372203534},
{"learn":[3.15819426],"iteration":919,"passed_time":0.6100478871,"remaining_time":0.05304764235},
{"learn":[3.157086603],"iteration":920,"passed_time":0.610598954,"remaining_time":0.05237493742},
{"learn":[3.153354154],"iteration":921,"passed_time":0.6111773231,"remaining_time":0.05170480607},
{"learn":[3.153261317],"iteration":922,"passed_time":0.6117365411,"remaining_time":0.05103327591},
{"learn":[3.153168454],"iteration":923,"passed_time":0.6123128375,"remaining_time":0.05036339356},
{"learn":[3.152080399],"iteration":924,"passed_time":0.6128769509,"remaining_time":0.04969272575},
{"learn":[3.151635144],"iteration":925,"passed_time":0.6134159747,"remaining_time":0.04902028307},
{"learn":[3.147762655],"iteration":926,"passed_time":0.6139607436,"remaining_time":0.04834858067},
{"learn":[3.147172317],"iteration":927,"passed_time":0.6145060949,"remaining_time":0.04767719702},
{"learn":[3.146254125],"iteration":928,"passed_time":0.6149985587,"remaining_time":0.0470020427},
{"learn":[3.144869828],"iteration":929,"passed_time":0.6155047261,"remaining_time":0.04632831272},
{"learn":[3.143466218],"iteration":930,"passed_time":0.6160594993,"remaining_time":0.04565854506},
{"learn":[3.141919643],"iteration":931,"passed_time":0.6166603767,"remaining_time":0.044992388},
{"learn":[3.141054135],"iteration":932,"passed_time":0.6172035095,"remaining_time":0.04432222415},
{"learn":[3.139390417],"iteration":933,"passed_time":0.6177917574,"remaining_time":0.04365552033},
{"learn":[3.139025283],"iteration":934,"passed_time":0.618392696,"remaining_time":0.04298986657},
{"learn":[3.137824183],"iteration":935,"passed_time":0.6191001473,"remaining_time":0.042331634},
{"learn":[3.135620453],"iteration":936,"passed_time":0.6197210389,"remaining_time":0.04166747646},
{"learn":[3.13443178],"iteration":937,"passed_time":0.6202942791,"remaining_time":0.04100026152},
{"learn":[3.132765713],"iteration":938,"passed_time":0.6208383128,"remaining_time":0.04033134939},
{"learn":[3.131434124],"iteration":939,"passed_time":0.6214508063,"remaining_time":0.03966707274},
{"learn":[3.128384262],"iteration":940,"passed_time":0.6220727177,"remaining_time":0.03900349665},
{"learn":[3.128120455],"iteration":941,"passed_time":0.6226930412,"remaining_time":0.03833991124},
{"learn":[3.126314615],"iteration":942,"passed_time":0.6232697781,"remaining_time":0.03767378298},
{"learn":[3.125409666],"iteration":943,"passed_time":0.6237796197,"remaining_time":0.03700387574},
{"learn":[3.123072589],"iteration":944,"passed_time":0.6244263496,"remaining_time":0.03634227431},
{"learn":[3.122921099],"iteration":945,"passed_time":0.6250090268,"remaining_time":0.03567704804},
{"learn":[3.122182662],"iteration":946,"passed_time":0.6255796722,"remaining_time":0.03501132273},
{"learn":[3.120040951],"iteration":947,"passed_time":0.6262294904,"remaining_time":0.03435014082},
{"learn":[3.118767799],"iteration":948,"passed_time":0.6267958936,"remaining_time":0.03368450008},
{"learn":[3.118203218],"iteration":949,"passed_time":0.6273862941,"remaining_time":0.03302033127},
{"learn":[3.116343362],"iteration":950,"passed_time":0.6279283935,"remaining_time":0.0323538289},
{"learn":[3.11480829],"iteration":951,"passed_time":0.6285163927,"remaining_time":0.03168990216},
{"learn":[3.112607903],"iteration":952,"passed_time":0.629130505,"remaining_time":0.0310274226},
{"learn":[3.111661241],"iteration":953,"passed_time":0.6297208131,"remaining_time":0.03036389665},
{"learn":[3.110249676],"iteration":954,"passed_time":0.6303018408,"remaining_time":0.02970008674},
{"learn":[3.107333579],"iteration":955,"passed_time":0.6308560801,"remaining_time":0.02903521708},
{"learn":[3.107149851],"iteration":956,"passed_time":0.6313578782,"remaining_time":0.02836822232},
{"learn":[3.106867336],"iteration":957,"passed_time":0.6318862319,"remaining_time":0.02770273668},
{"learn":[3.10364681],"iteration":958,"passed_time":0.6325044254,"remaining_time":0.02704137794},
{"learn":[3.102703811],"iteration":959,"passed_time":0.6331883107,"remaining_time":0.02638284628},
{"learn":[3.101469264],"iteration":960,"passed_time":0.6338666575,"remaining_time":0.02572403709},
{"learn":[3.09863569],"iteration":961,"passed_time":0.6346658659,"remaining_time":0.02506996144},
{"learn":[3.09645939],"iteration":962,"passed_time":0.6353015044,"remaining_time":0.02440929975},
{"learn":[3.096240186],"iteration":963,"passed_time":0.6358422064,"remaining_time":0.02374514464},
{"learn":[3.094838828],"iteration":964,"passed_time":0.6364013398,"remaining_time":0.02308191388},
{"learn":[3.094176802],"iteration":965,"passed_time":0.6369992986,"remaining_time":0.02242026517},
{"learn":[3.093182279],"iteration":966,"passed_time":0.6375608268,"remaining_time":0.02175750495},
{"learn":[3.090150687],"iteration":967,"passed_time":0.6381296438,"remaining_time":0.02109519484},
{"learn":[3.088612829],"iteration":968,"passed_time":0.6386862788,"remaining_time":0.02043268797},
{"learn":[3.087153684],"iteration":969,"passed_time":0.6392367511,"remaining_time":0.0197702088},
{"learn":[3.085866843],"iteration":970,"passed_time":0.6398180965,"remaining_time":0.01910888239},
{"learn":[3.082669094],"iteration":971,"passed_time":0.6403660552,"remaining_time":0.01844675879},
{"learn":[3.081047548],"iteration":972,"passed_time":0.6409677433,"remaining_time":0.01778636081},
{"learn":[3.079684322],"iteration":973,"passed_time":0.6415361827,"remaining_time":0.01712519584},
{"learn":[3.07613431],"iteration":974,"passed_time":0.6420632024,"remaining_time":0.01646315904},
{"learn":[3.074005935],"iteration":975,"passed_time":0.6426370571,"remaining_time":0.01580255058},
{"learn":[3.072988853],"iteration":976,"passed_time":0.6431759871,"remaining_time":0.01514129755},
{"learn":[3.072344268],"iteration":977,"passed_time":0.6437009966,"remaining_time":0.01447998152},
{"learn":[3.070654438],"iteration":978,"passed_time":0.6442915763,"remaining_time":0.01382035046},
{"learn":[3.069724506],"iteration":979,"passed_time":0.6448208597,"remaining_time":0.01315960938},
{"learn":[3.067763166],"iteration":980,"passed_time":0.6454251899,"remaining_time":0.01250058981},
{"learn":[3.066737893],"iteration":981,"passed_time":0.6460155587,"remaining_time":0.01184142572},
{"learn":[3.065248174],"iteration":982,"passed_time":0.6465710531,"remaining_time":0.01118179848},
{"learn":[3.063186837],"iteration":983,"passed_time":0.6471016037,"remaining_time":0.0105219773},
{"learn":[3.062880371],"iteration":984,"passed_time":0.6475871463,"remaining_time":0.009861733193},
{"learn":[3.061288645],"iteration":985,"passed_time":0.6484990708,"remaining_time":0.009207897557},
{"learn":[3.059970575],"iteration":986,"passed_time":0.6490962545,"remaining_time":0.008549393424},
{"learn":[3.059576341],"iteration":987,"passed_time":0.6497363852,"remaining_time":0.007891535043},
{"learn":[3.058175919],"iteration":988,"passed_time":0.6503239496,"remaining_time":0.007233127852},
{"learn":[3.056830702],"iteration":989,"passed_time":0.6508453717,"remaining_time":0.006574195674},
{"learn":[3.056336579],"iteration":990,"passed_time":0.651370517,"remaining_time":0.005915574826},
{"learn":[3.055810414],"iteration":991,"passed_time":0.6519742739,"remaining_time":0.005257857048},
{"learn":[3.055476518],"iteration":992,"passed_time":0.6525282156,"remaining_time":0.004599896786},
{"learn":[3.053331734],"iteration":993,"passed_time":0.6530333779,"remaining_time":0.003941851376},
{"learn":[3.050890374],"iteration":994,"passed_time":0.6535562261,"remaining_time":0.003284202141},
{"learn":[3.04972623],"iteration":995,"passed_time":0.6540867645,"remaining_time":0.002626854476},
{"learn":[3.047217327],"iteration":996,"passed_time":0.6546296855,"remaining_time":0.001969798452},
{"learn":[3.047155483],"iteration":997,"passed_time":0.6551091622,"remaining_time":0.001312844012},
{"learn":[3.04430671],"iteration":998,"passed_time":0.6556031507,"remaining_time":0.0006562594101},
{"learn":[3.042664195],"iteration":999,"passed_time":0.6561476119,"remaining_time":0}
]}